{
"meta":{"test_sets":[],"test_metrics":[],"learn_metrics":[{"best_value":"Min","name":"RMSE"}],"launch_mode":"Train","parameters":"","iteration_count":1000,"learn_sets":["learn"],"name":"experiment"},
"iterations":[
{"learn":[14.61268541],"iteration":0,"passed_time":0.1521240037,"remaining_time":151.9718797},
{"learn":[14.23196558],"iteration":1,"passed_time":0.1526884082,"remaining_time":76.1915157},
{"learn":[13.86674177],"iteration":2,"passed_time":0.1534235095,"remaining_time":50.98774632},
{"learn":[13.49946468],"iteration":3,"passed_time":0.1539229022,"remaining_time":38.32680264},
{"learn":[13.16661202],"iteration":4,"passed_time":0.1544576984,"remaining_time":30.73708198},
{"learn":[12.85632158],"iteration":5,"passed_time":0.1551832647,"remaining_time":25.70869418},
{"learn":[12.56784336],"iteration":6,"passed_time":0.1558363829,"remaining_time":22.10650404},
{"learn":[12.31617801],"iteration":7,"passed_time":0.1564551025,"remaining_time":19.40043271},
{"learn":[12.01509946],"iteration":8,"passed_time":0.1572378891,"remaining_time":17.31363868},
{"learn":[11.71512571],"iteration":9,"passed_time":0.1578893355,"remaining_time":15.63104421},
{"learn":[11.43264457],"iteration":10,"passed_time":0.1585962848,"remaining_time":14.25924779},
{"learn":[11.17973129],"iteration":11,"passed_time":0.1591457408,"remaining_time":13.10299932},
{"learn":[10.93746433],"iteration":12,"passed_time":0.1597855989,"remaining_time":12.13141432},
{"learn":[10.69387075],"iteration":13,"passed_time":0.1605063827,"remaining_time":11.30423524},
{"learn":[10.4615922],"iteration":14,"passed_time":0.1611866421,"remaining_time":10.5845895},
{"learn":[10.2299235],"iteration":15,"passed_time":0.1617485219,"remaining_time":9.947534098},
{"learn":[10.01419731],"iteration":16,"passed_time":0.1623777702,"remaining_time":9.389255769},
{"learn":[9.795856918],"iteration":17,"passed_time":0.1629463861,"remaining_time":8.889630622},
{"learn":[9.60040151],"iteration":18,"passed_time":0.1636695342,"remaining_time":8.450516477},
{"learn":[9.418664989],"iteration":19,"passed_time":0.1643953299,"remaining_time":8.055371163},
{"learn":[9.249278645],"iteration":20,"passed_time":0.1649612814,"remaining_time":7.690337833},
{"learn":[9.090113396],"iteration":21,"passed_time":0.165615645,"remaining_time":7.362368218},
{"learn":[8.909548708],"iteration":22,"passed_time":0.1662146826,"remaining_time":7.060510648},
{"learn":[8.740140208],"iteration":23,"passed_time":0.1668225633,"remaining_time":6.784117572},
{"learn":[8.59377682],"iteration":24,"passed_time":0.1677131275,"remaining_time":6.540811973},
{"learn":[8.453885414],"iteration":25,"passed_time":0.1682859726,"remaining_time":6.304251435},
{"learn":[8.317732234],"iteration":26,"passed_time":0.1689452534,"remaining_time":6.088286354},
{"learn":[8.180896085],"iteration":27,"passed_time":0.169883143,"remaining_time":5.897371965},
{"learn":[8.053220863],"iteration":28,"passed_time":0.1704420999,"remaining_time":5.706871691},
{"learn":[7.924234474],"iteration":29,"passed_time":0.1710915428,"remaining_time":5.531959885},
{"learn":[7.818879511],"iteration":30,"passed_time":0.1717952816,"remaining_time":5.369987997},
{"learn":[7.719346395],"iteration":31,"passed_time":0.1727328316,"remaining_time":5.225168156},
{"learn":[7.624163594],"iteration":32,"passed_time":0.1735004304,"remaining_time":5.084088369},
{"learn":[7.524952543],"iteration":33,"passed_time":0.1741597269,"remaining_time":4.948185181},
{"learn":[7.424464745],"iteration":34,"passed_time":0.1747541471,"remaining_time":4.818221484},
{"learn":[7.327482321],"iteration":35,"passed_time":0.1753526961,"remaining_time":4.695555529},
{"learn":[7.238666841],"iteration":36,"passed_time":0.1759684778,"remaining_time":4.579936327},
{"learn":[7.158842395],"iteration":37,"passed_time":0.176540881,"remaining_time":4.469271776},
{"learn":[7.074348246],"iteration":38,"passed_time":0.1771434277,"remaining_time":4.364995745},
{"learn":[6.992269093],"iteration":39,"passed_time":0.1777670951,"remaining_time":4.266410283},
{"learn":[6.925219745],"iteration":40,"passed_time":0.1784154563,"remaining_time":4.173181038},
{"learn":[6.86013671],"iteration":41,"passed_time":0.1790121059,"remaining_time":4.083180892},
{"learn":[6.786739622],"iteration":42,"passed_time":0.1796481531,"remaining_time":3.998215873},
{"learn":[6.73057926],"iteration":43,"passed_time":0.1801947107,"remaining_time":3.915139623},
{"learn":[6.666356486],"iteration":44,"passed_time":0.1808304351,"remaining_time":3.837623678},
{"learn":[6.606182832],"iteration":45,"passed_time":0.1814838275,"remaining_time":3.763816771},
{"learn":[6.547854615],"iteration":46,"passed_time":0.1822385284,"remaining_time":3.69517697},
{"learn":[6.49240675],"iteration":47,"passed_time":0.1828724791,"remaining_time":3.626970835},
{"learn":[6.431317261],"iteration":48,"passed_time":0.1834386037,"remaining_time":3.56020637},
{"learn":[6.377586395],"iteration":49,"passed_time":0.1839597239,"remaining_time":3.495234754},
{"learn":[6.327558015],"iteration":50,"passed_time":0.1845726248,"remaining_time":3.434498449},
{"learn":[6.282040317],"iteration":51,"passed_time":0.1854395166,"remaining_time":3.380705033},
{"learn":[6.237655841],"iteration":52,"passed_time":0.1860738103,"remaining_time":3.3247528},
{"learn":[6.192792003],"iteration":53,"passed_time":0.1867798992,"remaining_time":3.272107122},
{"learn":[6.150579347],"iteration":54,"passed_time":0.1874442864,"remaining_time":3.220633648},
{"learn":[6.115693845],"iteration":55,"passed_time":0.1880636305,"remaining_time":3.170215485},
{"learn":[6.078780782],"iteration":56,"passed_time":0.1886368596,"remaining_time":3.12078173},
{"learn":[6.045146957],"iteration":57,"passed_time":0.1892756517,"remaining_time":3.074097653},
{"learn":[6.008080327],"iteration":58,"passed_time":0.1898130947,"remaining_time":3.027358002},
{"learn":[5.977575734],"iteration":59,"passed_time":0.1903637168,"remaining_time":2.982364896},
{"learn":[5.948036502],"iteration":60,"passed_time":0.1909826366,"remaining_time":2.939880258},
{"learn":[5.914888282],"iteration":61,"passed_time":0.1916290225,"remaining_time":2.899161663},
{"learn":[5.884957796],"iteration":62,"passed_time":0.1921423351,"remaining_time":2.857736},
{"learn":[5.849539885],"iteration":63,"passed_time":0.1927844552,"remaining_time":2.819472658},
{"learn":[5.821387627],"iteration":64,"passed_time":0.1933728546,"remaining_time":2.78159414},
{"learn":[5.797012279],"iteration":65,"passed_time":0.1941387114,"remaining_time":2.747356917},
{"learn":[5.768685095],"iteration":66,"passed_time":0.194648233,"remaining_time":2.710549275},
{"learn":[5.755484587],"iteration":67,"passed_time":0.1949701399,"remaining_time":2.6722378},
{"learn":[5.731887055],"iteration":68,"passed_time":0.1955168182,"remaining_time":2.638060257},
{"learn":[5.707148487],"iteration":69,"passed_time":0.1961620955,"remaining_time":2.606153555},
{"learn":[5.685365039],"iteration":70,"passed_time":0.1967504953,"remaining_time":2.574383241},
{"learn":[5.663541834],"iteration":71,"passed_time":0.1974016327,"remaining_time":2.54428771},
{"learn":[5.638108797],"iteration":72,"passed_time":0.1979556731,"remaining_time":2.513765877},
{"learn":[5.619204893],"iteration":73,"passed_time":0.1984967361,"remaining_time":2.483891589},
{"learn":[5.598472793],"iteration":74,"passed_time":0.1991322261,"remaining_time":2.455964122},
{"learn":[5.577007075],"iteration":75,"passed_time":0.1997197451,"remaining_time":2.428171638},
{"learn":[5.562637084],"iteration":76,"passed_time":0.2003685382,"remaining_time":2.401820269},
{"learn":[5.54729991],"iteration":77,"passed_time":0.2009015986,"remaining_time":2.374759922},
{"learn":[5.530737623],"iteration":78,"passed_time":0.2014676424,"remaining_time":2.348755679},
{"learn":[5.513704873],"iteration":79,"passed_time":0.20202882,"remaining_time":2.32333143},
{"learn":[5.501575529],"iteration":80,"passed_time":0.202630576,"remaining_time":2.298981473},
{"learn":[5.484080734],"iteration":81,"passed_time":0.2032513373,"remaining_time":2.275423508},
{"learn":[5.472178894],"iteration":82,"passed_time":0.2038790339,"remaining_time":2.252494869},
{"learn":[5.458923342],"iteration":83,"passed_time":0.2044766781,"remaining_time":2.229769489},
{"learn":[5.451382371],"iteration":84,"passed_time":0.2048483442,"remaining_time":2.205132176},
{"learn":[5.441410748],"iteration":85,"passed_time":0.205489625,"remaining_time":2.183924619},
{"learn":[5.434047468],"iteration":86,"passed_time":0.2058936435,"remaining_time":2.16069996},
{"learn":[5.422107497],"iteration":87,"passed_time":0.2064695295,"remaining_time":2.139775124},
{"learn":[5.40731265],"iteration":88,"passed_time":0.2070744692,"remaining_time":2.11960496},
{"learn":[5.396360181],"iteration":89,"passed_time":0.2076863071,"remaining_time":2.099939327},
{"learn":[5.383793239],"iteration":90,"passed_time":0.2082860313,"remaining_time":2.080571455},
{"learn":[5.369605034],"iteration":91,"passed_time":0.2088993078,"remaining_time":2.061745342},
{"learn":[5.357467333],"iteration":92,"passed_time":0.2094687601,"remaining_time":2.042883499},
{"learn":[5.341109968],"iteration":93,"passed_time":0.2100483923,"remaining_time":2.024508973},
{"learn":[5.330529276],"iteration":94,"passed_time":0.2105734582,"remaining_time":2.00598926},
{"learn":[5.319862075],"iteration":95,"passed_time":0.2114346911,"remaining_time":1.991010008},
{"learn":[5.313052243],"iteration":96,"passed_time":0.212093028,"remaining_time":1.974433033},
{"learn":[5.299677207],"iteration":97,"passed_time":0.2126920123,"remaining_time":1.957634644},
{"learn":[5.287546698],"iteration":98,"passed_time":0.2133215114,"remaining_time":1.94144123},
{"learn":[5.279803754],"iteration":99,"passed_time":0.2139565833,"remaining_time":1.925609249},
{"learn":[5.272254612],"iteration":100,"passed_time":0.2145274689,"remaining_time":1.909506877},
{"learn":[5.268813888],"iteration":101,"passed_time":0.2148959568,"remaining_time":1.891927149},
{"learn":[5.258113767],"iteration":102,"passed_time":0.2155029004,"remaining_time":1.876758268},
{"learn":[5.251018576],"iteration":103,"passed_time":0.2161371979,"remaining_time":1.86210509},
{"learn":[5.24171237],"iteration":104,"passed_time":0.2167443686,"remaining_time":1.847487714},
{"learn":[5.233984943],"iteration":105,"passed_time":0.2174197927,"remaining_time":1.833710327},
{"learn":[5.226240449],"iteration":106,"passed_time":0.2180734222,"remaining_time":1.819995944},
{"learn":[5.220541644],"iteration":107,"passed_time":0.2186743775,"remaining_time":1.806088377},
{"learn":[5.211712096],"iteration":108,"passed_time":0.2192629852,"remaining_time":1.792324035},
{"learn":[5.203388597],"iteration":109,"passed_time":0.2198550569,"remaining_time":1.778827279},
{"learn":[5.196026544],"iteration":110,"passed_time":0.2204485106,"remaining_time":1.765574108},
{"learn":[5.188716772],"iteration":111,"passed_time":0.2210686662,"remaining_time":1.75275871},
{"learn":[5.182163132],"iteration":112,"passed_time":0.2216541128,"remaining_time":1.739886708},
{"learn":[5.17764747],"iteration":113,"passed_time":0.2222119106,"remaining_time":1.727015375},
{"learn":[5.170548056],"iteration":114,"passed_time":0.2228371533,"remaining_time":1.714877223},
{"learn":[5.165901827],"iteration":115,"passed_time":0.22338566,"remaining_time":1.702352789},
{"learn":[5.160333668],"iteration":116,"passed_time":0.2240844062,"remaining_time":1.691166929},
{"learn":[5.148953243],"iteration":117,"passed_time":0.2247444708,"remaining_time":1.679869689},
{"learn":[5.144729126],"iteration":118,"passed_time":0.2251749626,"remaining_time":1.667051614},
{"learn":[5.139939946],"iteration":119,"passed_time":0.2257531657,"remaining_time":1.655523215},
{"learn":[5.132898872],"iteration":120,"passed_time":0.2263675811,"remaining_time":1.644438874},
{"learn":[5.129073077],"iteration":121,"passed_time":0.2269380723,"remaining_time":1.633210061},
{"learn":[5.127123916],"iteration":122,"passed_time":0.2272586481,"remaining_time":1.620372637},
{"learn":[5.121282057],"iteration":123,"passed_time":0.2277931544,"remaining_time":1.609248414},
{"learn":[5.114489821],"iteration":124,"passed_time":0.2283559055,"remaining_time":1.598491338},
{"learn":[5.107777291],"iteration":125,"passed_time":0.2289536323,"remaining_time":1.588138687},
{"learn":[5.103518754],"iteration":126,"passed_time":0.2295970911,"remaining_time":1.57825402},
{"learn":[5.101133351],"iteration":127,"passed_time":0.2299861742,"remaining_time":1.566780812},
{"learn":[5.096462705],"iteration":128,"passed_time":0.2308106533,"remaining_time":1.558419217},
{"learn":[5.08562082],"iteration":129,"passed_time":0.2315007386,"remaining_time":1.549274174},
{"learn":[5.080483682],"iteration":130,"passed_time":0.2320865754,"remaining_time":1.539566672},
{"learn":[5.07437499],"iteration":131,"passed_time":0.2327104266,"remaining_time":1.530247351},
{"learn":[5.070683732],"iteration":132,"passed_time":0.2333043712,"remaining_time":1.520863834},
{"learn":[5.06432037],"iteration":133,"passed_time":0.2338743554,"remaining_time":1.511456655},
{"learn":[5.057436484],"iteration":134,"passed_time":0.2345030511,"remaining_time":1.502556587},
{"learn":[5.053254656],"iteration":135,"passed_time":0.2351230194,"remaining_time":1.493722711},
{"learn":[5.04801663],"iteration":136,"passed_time":0.2357669217,"remaining_time":1.485159514},
{"learn":[5.045680836],"iteration":137,"passed_time":0.2362693192,"remaining_time":1.475827197},
{"learn":[5.041857933],"iteration":138,"passed_time":0.2368847329,"remaining_time":1.467321978},
{"learn":[5.035264888],"iteration":139,"passed_time":0.2375460026,"remaining_time":1.459211159},
{"learn":[5.028771948],"iteration":140,"passed_time":0.2381806686,"remaining_time":1.451043931},
{"learn":[5.024912247],"iteration":141,"passed_time":0.2388513209,"remaining_time":1.443200235},
{"learn":[5.02239068],"iteration":142,"passed_time":0.239420352,"remaining_time":1.434847844},
{"learn":[5.017110572],"iteration":143,"passed_time":0.2403184298,"remaining_time":1.428559555},
{"learn":[5.010707886],"iteration":144,"passed_time":0.2408855516,"remaining_time":1.420394114},
{"learn":[5.004389868],"iteration":145,"passed_time":0.2414392654,"remaining_time":1.412254333},
{"learn":[4.997628683],"iteration":146,"passed_time":0.2420366047,"remaining_time":1.40447091},
{"learn":[4.991497851],"iteration":147,"passed_time":0.2427086693,"remaining_time":1.397214772},
{"learn":[4.988345253],"iteration":148,"passed_time":0.2435335267,"remaining_time":1.390919672},
{"learn":[4.98460423],"iteration":149,"passed_time":0.24418873,"remaining_time":1.383736137},
{"learn":[4.982441783],"iteration":150,"passed_time":0.2447544258,"remaining_time":1.376135811},
{"learn":[4.977461771],"iteration":151,"passed_time":0.2453607854,"remaining_time":1.368854908},
{"learn":[4.973601586],"iteration":152,"passed_time":0.245856348,"remaining_time":1.361047887},
{"learn":[4.968328804],"iteration":153,"passed_time":0.2464734114,"remaining_time":1.354003286},
{"learn":[4.9640736],"iteration":154,"passed_time":0.2469859903,"remaining_time":1.346472012},
{"learn":[4.960865882],"iteration":155,"passed_time":0.2475605314,"remaining_time":1.339365952},
{"learn":[4.957014156],"iteration":156,"passed_time":0.2481163781,"remaining_time":1.332242718},
{"learn":[4.952244852],"iteration":157,"passed_time":0.2487911673,"remaining_time":1.325836474},
{"learn":[4.949695675],"iteration":158,"passed_time":0.249389372,"remaining_time":1.319097244},
{"learn":[4.946584698],"iteration":159,"passed_time":0.2500995957,"remaining_time":1.313022878},
{"learn":[4.940192834],"iteration":160,"passed_time":0.2507776475,"remaining_time":1.306847492},
{"learn":[4.936727994],"iteration":161,"passed_time":0.251415105,"remaining_time":1.300529988},
{"learn":[4.932342063],"iteration":162,"passed_time":0.2519757438,"remaining_time":1.293887715},
{"learn":[4.925830838],"iteration":163,"passed_time":0.2525406579,"remaining_time":1.287341403},
{"learn":[4.922571773],"iteration":164,"passed_time":0.2531251974,"remaining_time":1.280966908},
{"learn":[4.918395814],"iteration":165,"passed_time":0.253783921,"remaining_time":1.27503488},
{"learn":[4.911142452],"iteration":166,"passed_time":0.2543612675,"remaining_time":1.268760095},
{"learn":[4.908276131],"iteration":167,"passed_time":0.2550586982,"remaining_time":1.263147839},
{"learn":[4.904584645],"iteration":168,"passed_time":0.2556191068,"remaining_time":1.256919987},
{"learn":[4.89795517],"iteration":169,"passed_time":0.2562845034,"remaining_time":1.251271399},
{"learn":[4.895556491],"iteration":170,"passed_time":0.2569273607,"remaining_time":1.245571825},
{"learn":[4.890591233],"iteration":171,"passed_time":0.257532493,"remaining_time":1.239749443},
{"learn":[4.884629277],"iteration":172,"passed_time":0.2582260416,"remaining_time":1.234410037},
{"learn":[4.880550786],"iteration":173,"passed_time":0.2588228334,"remaining_time":1.228664715},
{"learn":[4.876384842],"iteration":174,"passed_time":0.2593868951,"remaining_time":1.222823934},
{"learn":[4.872638238],"iteration":175,"passed_time":0.2600382359,"remaining_time":1.217451741},
{"learn":[4.869137118],"iteration":176,"passed_time":0.2606385762,"remaining_time":1.211895753},
{"learn":[4.863587157],"iteration":177,"passed_time":0.2612692068,"remaining_time":1.206535326},
{"learn":[4.858028614],"iteration":178,"passed_time":0.2618764966,"remaining_time":1.201120691},
{"learn":[4.853838176],"iteration":179,"passed_time":0.2624377691,"remaining_time":1.195549837},
{"learn":[4.853462329],"iteration":180,"passed_time":0.2627333824,"remaining_time":1.188832266},
{"learn":[4.851573196],"iteration":181,"passed_time":0.2633814755,"remaining_time":1.183769489},
{"learn":[4.848442087],"iteration":182,"passed_time":0.2640584845,"remaining_time":1.178884054},
{"learn":[4.845547104],"iteration":183,"passed_time":0.2646051734,"remaining_time":1.173466421},
{"learn":[4.839868817],"iteration":184,"passed_time":0.2652017136,"remaining_time":1.168321062},
{"learn":[4.836336958],"iteration":185,"passed_time":0.2658114978,"remaining_time":1.163282576},
{"learn":[4.831124789],"iteration":186,"passed_time":0.266418065,"remaining_time":1.15827747},
{"learn":[4.827407333],"iteration":187,"passed_time":0.2669788508,"remaining_time":1.153121419},
{"learn":[4.824088918],"iteration":188,"passed_time":0.267573387,"remaining_time":1.148158819},
{"learn":[4.820934539],"iteration":189,"passed_time":0.2681834278,"remaining_time":1.143308297},
{"learn":[4.816975227],"iteration":190,"passed_time":0.2686961216,"remaining_time":1.138089855},
{"learn":[4.812340486],"iteration":191,"passed_time":0.2692206376,"remaining_time":1.132970183},
{"learn":[4.806402747],"iteration":192,"passed_time":0.2698266285,"remaining_time":1.128238804},
{"learn":[4.801521788],"iteration":193,"passed_time":0.2705156941,"remaining_time":1.1238951},
{"learn":[4.797601172],"iteration":194,"passed_time":0.2711445296,"remaining_time":1.119340237},
{"learn":[4.792694629],"iteration":195,"passed_time":0.2717141527,"remaining_time":1.114582545},
{"learn":[4.789794613],"iteration":196,"passed_time":0.2722859382,"remaining_time":1.109876185},
{"learn":[4.785367055],"iteration":197,"passed_time":0.2729097293,"remaining_time":1.105422237},
{"learn":[4.780376856],"iteration":198,"passed_time":0.273527256,"remaining_time":1.100981568},
{"learn":[4.776691261],"iteration":199,"passed_time":0.2741089992,"remaining_time":1.096435997},
{"learn":[4.773470753],"iteration":200,"passed_time":0.2747168879,"remaining_time":1.092033798},
{"learn":[4.77207327],"iteration":201,"passed_time":0.2755429255,"remaining_time":1.088530963},
{"learn":[4.767347177],"iteration":202,"passed_time":0.2760861236,"remaining_time":1.083944042},
{"learn":[4.763983068],"iteration":203,"passed_time":0.2767663343,"remaining_time":1.079931383},
{"learn":[4.761588849],"iteration":204,"passed_time":0.2773418228,"remaining_time":1.075545118},
{"learn":[4.758558086],"iteration":205,"passed_time":0.2779268244,"remaining_time":1.071232518},
{"learn":[4.753678804],"iteration":206,"passed_time":0.2785374051,"remaining_time":1.067053924},
{"learn":[4.746510889],"iteration":207,"passed_time":0.2791054969,"remaining_time":1.062747854},
{"learn":[4.744840601],"iteration":208,"passed_time":0.2797228386,"remaining_time":1.058663949},
{"learn":[4.741702222],"iteration":209,"passed_time":0.2803074516,"remaining_time":1.054489937},
{"learn":[4.739352853],"iteration":210,"passed_time":0.2809565889,"remaining_time":1.050591226},
{"learn":[4.735539287],"iteration":211,"passed_time":0.2815728397,"remaining_time":1.046600932},
{"learn":[4.730726751],"iteration":212,"passed_time":0.2821371466,"remaining_time":1.042450396},
{"learn":[4.726416092],"iteration":213,"passed_time":0.2826612586,"remaining_time":1.038185744},
{"learn":[4.721293082],"iteration":214,"passed_time":0.2832301752,"remaining_time":1.034119477},
{"learn":[4.718443695],"iteration":215,"passed_time":0.2838669959,"remaining_time":1.030332059},
{"learn":[4.711627962],"iteration":216,"passed_time":0.2845550763,"remaining_time":1.026758639},
{"learn":[4.709790764],"iteration":217,"passed_time":0.2851643381,"remaining_time":1.022928956},
{"learn":[4.706913073],"iteration":218,"passed_time":0.2858474978,"remaining_time":1.019392218},
{"learn":[4.703846389],"iteration":219,"passed_time":0.2864744362,"remaining_time":1.015682092},
{"learn":[4.701001135],"iteration":220,"passed_time":0.2870630228,"remaining_time":1.011864682},
{"learn":[4.700380864],"iteration":221,"passed_time":0.2876748247,"remaining_time":1.008157719},
{"learn":[4.695837486],"iteration":222,"passed_time":0.2883824885,"remaining_time":1.004812527},
{"learn":[4.691242996],"iteration":223,"passed_time":0.2890141902,"remaining_time":1.00122773},
{"learn":[4.690284609],"iteration":224,"passed_time":0.2895804891,"remaining_time":0.9974439069},
{"learn":[4.68827119],"iteration":225,"passed_time":0.290135959,"remaining_time":0.9936514703},
{"learn":[4.686922425],"iteration":226,"passed_time":0.2907852472,"remaining_time":0.9902070314},
{"learn":[4.686085874],"iteration":227,"passed_time":0.2913554964,"remaining_time":0.9865194879},
{"learn":[4.683230741],"iteration":228,"passed_time":0.291960669,"remaining_time":0.9829767502},
{"learn":[4.6773487],"iteration":229,"passed_time":0.2925808035,"remaining_time":0.9795096464},
{"learn":[4.671462906],"iteration":230,"passed_time":0.293129466,"remaining_time":0.9758292614},
{"learn":[4.664799601],"iteration":231,"passed_time":0.2938908889,"remaining_time":0.9728801839},
{"learn":[4.660979386],"iteration":232,"passed_time":0.2945251822,"remaining_time":0.9695313939},
{"learn":[4.656281279],"iteration":233,"passed_time":0.2951066655,"remaining_time":0.9660329306},
{"learn":[4.651997094],"iteration":234,"passed_time":0.2957503568,"remaining_time":0.9627617997},
{"learn":[4.650151977],"iteration":235,"passed_time":0.2963666772,"remaining_time":0.959424328},
{"learn":[4.648478046],"iteration":236,"passed_time":0.2969352086,"remaining_time":0.9559559669},
{"learn":[4.646364602],"iteration":237,"passed_time":0.2976168867,"remaining_time":0.9528742339},
{"learn":[4.642635873],"iteration":238,"passed_time":0.2983897347,"remaining_time":0.9501028791},
{"learn":[4.640860821],"iteration":239,"passed_time":0.2990049653,"remaining_time":0.9468490569},
{"learn":[4.639446822],"iteration":240,"passed_time":0.2996057866,"remaining_time":0.9435717513},
{"learn":[4.637120072],"iteration":241,"passed_time":0.3001458666,"remaining_time":0.9401263093},
{"learn":[4.633769267],"iteration":242,"passed_time":0.3007815503,"remaining_time":0.9370026075},
{"learn":[4.630491517],"iteration":243,"passed_time":0.3013461689,"remaining_time":0.9336791135},
{"learn":[4.627813333],"iteration":244,"passed_time":0.3019750135,"remaining_time":0.9305760621},
{"learn":[4.622496304],"iteration":245,"passed_time":0.3025397918,"remaining_time":0.9272967602},
{"learn":[4.618979301],"iteration":246,"passed_time":0.3033563108,"remaining_time":0.924806891},
{"learn":[4.616563458],"iteration":247,"passed_time":0.3038946603,"remaining_time":0.9214870345},
{"learn":[4.614759385],"iteration":248,"passed_time":0.3044513663,"remaining_time":0.918244884},
{"learn":[4.61251363],"iteration":249,"passed_time":0.3051269114,"remaining_time":0.9153807342},
{"learn":[4.608796693],"iteration":250,"passed_time":0.3057655227,"remaining_time":0.9124238108},
{"learn":[4.60847774],"iteration":251,"passed_time":0.3063149523,"remaining_time":0.9092205727},
{"learn":[4.605195659],"iteration":252,"passed_time":0.3070049875,"remaining_time":0.9064534611},
{"learn":[4.60103766],"iteration":253,"passed_time":0.3076892347,"remaining_time":0.903685705},
{"learn":[4.599325598],"iteration":254,"passed_time":0.3082016995,"remaining_time":0.9004324161},
{"learn":[4.597012808],"iteration":255,"passed_time":0.308712626,"remaining_time":0.8971960694},
{"learn":[4.594161533],"iteration":256,"passed_time":0.3093714362,"remaining_time":0.8944084713},
{"learn":[4.592197259],"iteration":257,"passed_time":0.3100117906,"remaining_time":0.8915842971},
{"learn":[4.58952828],"iteration":258,"passed_time":0.3106622521,"remaining_time":0.8888059028},
{"learn":[4.585816572],"iteration":259,"passed_time":0.3112863074,"remaining_time":0.8859687212},
{"learn":[4.582934052],"iteration":260,"passed_time":0.3119997673,"remaining_time":0.8834016401},
{"learn":[4.582234842],"iteration":261,"passed_time":0.3125715697,"remaining_time":0.8804496887},
{"learn":[4.57571562],"iteration":262,"passed_time":0.3131402841,"remaining_time":0.8775071839},
{"learn":[4.571197349],"iteration":263,"passed_time":0.3137550732,"remaining_time":0.8747111132},
{"learn":[4.56723703],"iteration":264,"passed_time":0.314381137,"remaining_time":0.8719627762},
{"learn":[4.560335567],"iteration":265,"passed_time":0.314928972,"remaining_time":0.8690145319},
{"learn":[4.554709345],"iteration":266,"passed_time":0.315572926,"remaining_time":0.8663481452},
{"learn":[4.552806306],"iteration":267,"passed_time":0.3162459414,"remaining_time":0.8637762281},
{"learn":[4.550766241],"iteration":268,"passed_time":0.317026857,"remaining_time":0.8615116449},
{"learn":[4.549216045],"iteration":269,"passed_time":0.3176445457,"remaining_time":0.8588167347},
{"learn":[4.547687452],"iteration":270,"passed_time":0.318253708,"remaining_time":0.8561142183},
{"learn":[4.545642435],"iteration":271,"passed_time":0.3188432957,"remaining_time":0.8533747031},
{"learn":[4.543930359],"iteration":272,"passed_time":0.319618532,"remaining_time":0.8511453215},
{"learn":[4.541029943],"iteration":273,"passed_time":0.3202154497,"remaining_time":0.8484540748},
{"learn":[4.537781449],"iteration":274,"passed_time":0.3208485391,"remaining_time":0.8458734213},
{"learn":[4.53066128],"iteration":275,"passed_time":0.3214395513,"remaining_time":0.843196504},
{"learn":[4.526763956],"iteration":276,"passed_time":0.3220274731,"remaining_time":0.8405265815},
{"learn":[4.522036004],"iteration":277,"passed_time":0.3226389824,"remaining_time":0.8379328968},
{"learn":[4.515307629],"iteration":278,"passed_time":0.3232006976,"remaining_time":0.8352247419},
{"learn":[4.51109143],"iteration":279,"passed_time":0.3237707703,"remaining_time":0.8325534093},
{"learn":[4.508233494],"iteration":280,"passed_time":0.3244745608,"remaining_time":0.8302391786},
{"learn":[4.502555629],"iteration":281,"passed_time":0.3251643945,"remaining_time":0.8279008343},
{"learn":[4.500081355],"iteration":282,"passed_time":0.3258724876,"remaining_time":0.8256204015},
{"learn":[4.495281743],"iteration":283,"passed_time":0.326410571,"remaining_time":0.8229224254},
{"learn":[4.492138869],"iteration":284,"passed_time":0.327194213,"remaining_time":0.8208556572},
{"learn":[4.491708261],"iteration":285,"passed_time":0.3277465115,"remaining_time":0.818220312},
{"learn":[4.489398865],"iteration":286,"passed_time":0.3283763039,"remaining_time":0.8157920024},
{"learn":[4.485796373],"iteration":287,"passed_time":0.3290554819,"remaining_time":0.8134982746},
{"learn":[4.479542205],"iteration":288,"passed_time":0.3298407571,"remaining_time":0.8114767416},
{"learn":[4.475986993],"iteration":289,"passed_time":0.3304518896,"remaining_time":0.809037385},
{"learn":[4.468661855],"iteration":290,"passed_time":0.3311196083,"remaining_time":0.8067484616},
{"learn":[4.463785664],"iteration":291,"passed_time":0.3319561815,"remaining_time":0.8048800566},
{"learn":[4.460445831],"iteration":292,"passed_time":0.3326184128,"remaining_time":0.8025980132},
{"learn":[4.45692492],"iteration":293,"passed_time":0.3332032781,"remaining_time":0.8001412053},
{"learn":[4.454031688],"iteration":294,"passed_time":0.3337663397,"remaining_time":0.7976449813},
{"learn":[4.451672391],"iteration":295,"passed_time":0.3343270884,"remaining_time":0.7951563182},
{"learn":[4.45031553],"iteration":296,"passed_time":0.3348157141,"remaining_time":0.7925099227},
{"learn":[4.446782666],"iteration":297,"passed_time":0.3354666689,"remaining_time":0.7902604078},
{"learn":[4.444369689],"iteration":298,"passed_time":0.3362135897,"remaining_time":0.7882465765},
{"learn":[4.44411683],"iteration":299,"passed_time":0.3367313853,"remaining_time":0.7857065657},
{"learn":[4.440876943],"iteration":300,"passed_time":0.3373210694,"remaining_time":0.7833469353},
{"learn":[4.439336453],"iteration":301,"passed_time":0.3378702409,"remaining_time":0.7809053912},
{"learn":[4.436666901],"iteration":302,"passed_time":0.3385189432,"remaining_time":0.7787052918},
{"learn":[4.433043336],"iteration":303,"passed_time":0.3390586054,"remaining_time":0.7762657544},
{"learn":[4.431419305],"iteration":304,"passed_time":0.3396081487,"remaining_time":0.7738611912},
{"learn":[4.428859646],"iteration":305,"passed_time":0.3401773892,"remaining_time":0.7715134252},
{"learn":[4.424552441],"iteration":306,"passed_time":0.3408940504,"remaining_time":0.7695100226},
{"learn":[4.422706391],"iteration":307,"passed_time":0.3415607448,"remaining_time":0.7674027123},
{"learn":[4.421427994],"iteration":308,"passed_time":0.3421682605,"remaining_time":0.7651723884},
{"learn":[4.418733158],"iteration":309,"passed_time":0.3432952268,"remaining_time":0.7641087307},
{"learn":[4.415656941],"iteration":310,"passed_time":0.3439554171,"remaining_time":0.7620105543},
{"learn":[4.410747417],"iteration":311,"passed_time":0.3445907,"remaining_time":0.7598666717},
{"learn":[4.408126521],"iteration":312,"passed_time":0.3452442751,"remaining_time":0.7577725782},
{"learn":[4.407843853],"iteration":313,"passed_time":0.3458341185,"remaining_time":0.7555484245},
{"learn":[4.405219398],"iteration":314,"passed_time":0.3465083517,"remaining_time":0.7535181615},
{"learn":[4.402708465],"iteration":315,"passed_time":0.3472837955,"remaining_time":0.7517155574},
{"learn":[4.40104971],"iteration":316,"passed_time":0.3478736259,"remaining_time":0.7495195158},
{"learn":[4.400830038],"iteration":317,"passed_time":0.3484763654,"remaining_time":0.7473612616},
{"learn":[4.39784288],"iteration":318,"passed_time":0.34910197,"remaining_time":0.7452615723},
{"learn":[4.393741845],"iteration":319,"passed_time":0.3497974325,"remaining_time":0.743319544},
{"learn":[4.393425936],"iteration":320,"passed_time":0.3504160383,"remaining_time":0.7412227103},
{"learn":[4.390505974],"iteration":321,"passed_time":0.3510838305,"remaining_time":0.7392386245},
{"learn":[4.390305136],"iteration":322,"passed_time":0.3517603027,"remaining_time":0.737280882},
{"learn":[4.38568203],"iteration":323,"passed_time":0.3523666581,"remaining_time":0.7351847558},
{"learn":[4.383057135],"iteration":324,"passed_time":0.3529670857,"remaining_time":0.7330854858},
{"learn":[4.380662684],"iteration":325,"passed_time":0.3535245584,"remaining_time":0.7309066024},
{"learn":[4.37805727],"iteration":326,"passed_time":0.3540932732,"remaining_time":0.7287607733},
{"learn":[4.373708319],"iteration":327,"passed_time":0.3546503852,"remaining_time":0.7266007891},
{"learn":[4.36887921],"iteration":328,"passed_time":0.3552476709,"remaining_time":0.7245324837},
{"learn":[4.367895929],"iteration":329,"passed_time":0.3560144391,"remaining_time":0.7228171944},
{"learn":[4.362140573],"iteration":330,"passed_time":0.3566649695,"remaining_time":0.7208727027},
{"learn":[4.361931924],"iteration":331,"passed_time":0.3572657962,"remaining_time":0.7188359995},
{"learn":[4.359656377],"iteration":332,"passed_time":0.3578449945,"remaining_time":0.7167645985},
{"learn":[4.354281355],"iteration":333,"passed_time":0.3584086281,"remaining_time":0.7146710968},
{"learn":[4.348589447],"iteration":334,"passed_time":0.3589826186,"remaining_time":0.7126072876},
{"learn":[4.346355698],"iteration":335,"passed_time":0.3595746232,"remaining_time":0.7105879459},
{"learn":[4.343894047],"iteration":336,"passed_time":0.3603066143,"remaining_time":0.7088524787},
{"learn":[4.341561356],"iteration":337,"passed_time":0.3608796999,"remaining_time":0.70681172},
{"learn":[4.338869061],"iteration":338,"passed_time":0.3614620237,"remaining_time":0.7047976333},
{"learn":[4.333720063],"iteration":339,"passed_time":0.3621053523,"remaining_time":0.7029103898},
{"learn":[4.330892223],"iteration":340,"passed_time":0.3627238628,"remaining_time":0.7009824797},
{"learn":[4.328311474],"iteration":341,"passed_time":0.3634054972,"remaining_time":0.699183676},
{"learn":[4.324580133],"iteration":342,"passed_time":0.3640865979,"remaining_time":0.6973903639},
{"learn":[4.323354432],"iteration":343,"passed_time":0.3647818325,"remaining_time":0.6956304713},
{"learn":[4.323159553],"iteration":344,"passed_time":0.3653539209,"remaining_time":0.6936429513},
{"learn":[4.318639682],"iteration":345,"passed_time":0.3659345345,"remaining_time":0.6916797271},
{"learn":[4.312712208],"iteration":346,"passed_time":0.3664982793,"remaining_time":0.6896927273},
{"learn":[4.311461062],"iteration":347,"passed_time":0.3670524599,"remaining_time":0.687695988},
{"learn":[4.311178356],"iteration":348,"passed_time":0.3675600117,"remaining_time":0.6856205375},
{"learn":[4.311102505],"iteration":349,"passed_time":0.3680839009,"remaining_time":0.6835843873},
{"learn":[4.310232308],"iteration":350,"passed_time":0.3687942234,"remaining_time":0.6819015697},
{"learn":[4.305128197],"iteration":351,"passed_time":0.3694785043,"remaining_time":0.6801763374},
{"learn":[4.304595496],"iteration":352,"passed_time":0.370086257,"remaining_time":0.6783167374},
{"learn":[4.3004992],"iteration":353,"passed_time":0.3706738193,"remaining_time":0.6764273652},
{"learn":[4.297581524],"iteration":354,"passed_time":0.3712848994,"remaining_time":0.6745880566},
{"learn":[4.297355825],"iteration":355,"passed_time":0.3718674146,"remaining_time":0.6727039748},
{"learn":[4.295758715],"iteration":356,"passed_time":0.3724309369,"remaining_time":0.6707929759},
{"learn":[4.292500657],"iteration":357,"passed_time":0.3731166641,"remaining_time":0.6691086546},
{"learn":[4.290797586],"iteration":358,"passed_time":0.373795111,"remaining_time":0.6674168973},
{"learn":[4.286410608],"iteration":359,"passed_time":0.374461123,"remaining_time":0.665708663},
{"learn":[4.280278245],"iteration":360,"passed_time":0.3750648373,"remaining_time":0.6638959309},
{"learn":[4.279941283],"iteration":361,"passed_time":0.3756474391,"remaining_time":0.662052669},
{"learn":[4.274426275],"iteration":362,"passed_time":0.3762746643,"remaining_time":0.6602946589},
{"learn":[4.273567658],"iteration":363,"passed_time":0.3768668253,"remaining_time":0.6584815958},
{"learn":[4.269488271],"iteration":364,"passed_time":0.3775287261,"remaining_time":0.6567965509},
{"learn":[4.266838205],"iteration":365,"passed_time":0.3781610278,"remaining_time":0.6550658241},
{"learn":[4.263456509],"iteration":366,"passed_time":0.3787121917,"remaining_time":0.6532011372},
{"learn":[4.260360204],"iteration":367,"passed_time":0.3792965347,"remaining_time":0.6514005704},
{"learn":[4.255120549],"iteration":368,"passed_time":0.3798115425,"remaining_time":0.6494880307},
{"learn":[4.252582211],"iteration":369,"passed_time":0.380399963,"remaining_time":0.6477080451},
{"learn":[4.247857931],"iteration":370,"passed_time":0.3809715724,"remaining_time":0.6459059812},
{"learn":[4.245288911],"iteration":371,"passed_time":0.3815153568,"remaining_time":0.6440635593},
{"learn":[4.24048515],"iteration":372,"passed_time":0.3820842619,"remaining_time":0.6422703276},
{"learn":[4.2378365],"iteration":373,"passed_time":0.3827091757,"remaining_time":0.6405773903},
{"learn":[4.236751063],"iteration":374,"passed_time":0.3833580733,"remaining_time":0.6389301222},
{"learn":[4.233240093],"iteration":375,"passed_time":0.3839629866,"remaining_time":0.6372151693},
{"learn":[4.230358421],"iteration":376,"passed_time":0.3845028812,"remaining_time":0.6353986605},
{"learn":[4.225853583],"iteration":377,"passed_time":0.3850509636,"remaining_time":0.6336023793},
{"learn":[4.224702126],"iteration":378,"passed_time":0.385642742,"remaining_time":0.6318842818},
{"learn":[4.224361982],"iteration":379,"passed_time":0.3862021527,"remaining_time":0.6301193018},
{"learn":[4.223787954],"iteration":380,"passed_time":0.3868280951,"remaining_time":0.6284687424},
{"learn":[4.22144054],"iteration":381,"passed_time":0.3873323395,"remaining_time":0.6266266644},
{"learn":[4.217739335],"iteration":382,"passed_time":0.3879444117,"remaining_time":0.6249652795},
{"learn":[4.215611665],"iteration":383,"passed_time":0.3886017599,"remaining_time":0.6233819898},
{"learn":[4.210236863],"iteration":384,"passed_time":0.3891960989,"remaining_time":0.6217028593},
{"learn":[4.208454294],"iteration":385,"passed_time":0.3898136988,"remaining_time":0.6200663498},
{"learn":[4.207446501],"iteration":386,"passed_time":0.3905286195,"remaining_time":0.6185892604},
{"learn":[4.204985442],"iteration":387,"passed_time":0.3911516942,"remaining_time":0.6169712289},
{"learn":[4.202796622],"iteration":388,"passed_time":0.3917126504,"remaining_time":0.6152607439},
{"learn":[4.199774004],"iteration":389,"passed_time":0.3923945988,"remaining_time":0.6137453981},
{"learn":[4.199458358],"iteration":390,"passed_time":0.3930049478,"remaining_time":0.612122796},
{"learn":[4.19751254],"iteration":391,"passed_time":0.3936480241,"remaining_time":0.610556119},
{"learn":[4.195201346],"iteration":392,"passed_time":0.3942533571,"remaining_time":0.6089358468},
{"learn":[4.190593508],"iteration":393,"passed_time":0.3949791015,"remaining_time":0.6075059276},
{"learn":[4.187212054],"iteration":394,"passed_time":0.3954781342,"remaining_time":0.6057323321},
{"learn":[4.184984466],"iteration":395,"passed_time":0.3961336485,"remaining_time":0.6042038477},
{"learn":[4.182832144],"iteration":396,"passed_time":0.3967390378,"remaining_time":0.6026036266},
{"learn":[4.179752812],"iteration":397,"passed_time":0.3974175383,"remaining_time":0.6011189901},
{"learn":[4.17878934],"iteration":398,"passed_time":0.3981093602,"remaining_time":0.5996584599},
{"learn":[4.174548229],"iteration":399,"passed_time":0.3987610904,"remaining_time":0.5981416356},
{"learn":[4.168872556],"iteration":400,"passed_time":0.3994387381,"remaining_time":0.5966678408},
{"learn":[4.163926494],"iteration":401,"passed_time":0.4000728025,"remaining_time":0.5951331739},
{"learn":[4.159485076],"iteration":402,"passed_time":0.4007105101,"remaining_time":0.5936083735},
{"learn":[4.155926102],"iteration":403,"passed_time":0.4012641144,"remaining_time":0.5919638915},
{"learn":[4.153540115],"iteration":404,"passed_time":0.4018386084,"remaining_time":0.5903554864},
{"learn":[4.150983044],"iteration":405,"passed_time":0.4024046013,"remaining_time":0.5887397369},
{"learn":[4.146539132],"iteration":406,"passed_time":0.4030524405,"remaining_time":0.5872483961},
{"learn":[4.144869174],"iteration":407,"passed_time":0.4036721166,"remaining_time":0.585720326},
{"learn":[4.142825962],"iteration":408,"passed_time":0.4043630329,"remaining_time":0.5842996392},
{"learn":[4.142467378],"iteration":409,"passed_time":0.4049362418,"remaining_time":0.5827131284},
{"learn":[4.141800768],"iteration":410,"passed_time":0.4055043458,"remaining_time":0.5811242328},
{"learn":[4.140107084],"iteration":411,"passed_time":0.4061136835,"remaining_time":0.5795991405},
{"learn":[4.136243196],"iteration":412,"passed_time":0.4066642282,"remaining_time":0.5779949199},
{"learn":[4.133618439],"iteration":413,"passed_time":0.407213925,"remaining_time":0.5763945895},
{"learn":[4.131053025],"iteration":414,"passed_time":0.4077774974,"remaining_time":0.5748188819},
{"learn":[4.128379975],"iteration":415,"passed_time":0.4083821419,"remaining_time":0.5733056992},
{"learn":[4.127068571],"iteration":416,"passed_time":0.4089882787,"remaining_time":0.5717989604},
{"learn":[4.125969877],"iteration":417,"passed_time":0.4096001147,"remaining_time":0.5703044659},
{"learn":[4.123893633],"iteration":418,"passed_time":0.4102856657,"remaining_time":0.5689164004},
{"learn":[4.119643722],"iteration":419,"passed_time":0.411123974,"remaining_time":0.5677426307},
{"learn":[4.11465686],"iteration":420,"passed_time":0.4117090591,"remaining_time":0.5662221977},
{"learn":[4.111565986],"iteration":421,"passed_time":0.4123899158,"remaining_time":0.5648373728},
{"learn":[4.106322452],"iteration":422,"passed_time":0.4131380992,"remaining_time":0.5635477145},
{"learn":[4.104222175],"iteration":423,"passed_time":0.4137338045,"remaining_time":0.5620534703},
{"learn":[4.103008002],"iteration":424,"passed_time":0.4142608835,"remaining_time":0.5604706071},
{"learn":[4.099176337],"iteration":425,"passed_time":0.414879119,"remaining_time":0.5590155266},
{"learn":[4.096525716],"iteration":426,"passed_time":0.4154122736,"remaining_time":0.5574501939},
{"learn":[4.094967724],"iteration":427,"passed_time":0.4160490668,"remaining_time":0.556028192},
{"learn":[4.094683584],"iteration":428,"passed_time":0.4167581034,"remaining_time":0.5547060071},
{"learn":[4.091096563],"iteration":429,"passed_time":0.4175785713,"remaining_time":0.5535343852},
{"learn":[4.089178677],"iteration":430,"passed_time":0.4182170049,"remaining_time":0.5521240737},
{"learn":[4.085335077],"iteration":431,"passed_time":0.4187990066,"remaining_time":0.5506431383},
{"learn":[4.084852122],"iteration":432,"passed_time":0.4194324005,"remaining_time":0.5492336514},
{"learn":[4.080322952],"iteration":433,"passed_time":0.4200344196,"remaining_time":0.5477868237},
{"learn":[4.077449519],"iteration":434,"passed_time":0.4206249653,"remaining_time":0.5463289779},
{"learn":[4.076568374],"iteration":435,"passed_time":0.4212696089,"remaining_time":0.5449450905},
{"learn":[4.076071793],"iteration":436,"passed_time":0.4220131366,"remaining_time":0.5436919815},
{"learn":[4.075027644],"iteration":437,"passed_time":0.4226640504,"remaining_time":0.542322366},
{"learn":[4.07020837],"iteration":438,"passed_time":0.4232771615,"remaining_time":0.5409077166},
{"learn":[4.06833694],"iteration":439,"passed_time":0.4239096964,"remaining_time":0.5395214318},
{"learn":[4.063936568],"iteration":440,"passed_time":0.4245419752,"remaining_time":0.5381382407},
{"learn":[4.061734926],"iteration":441,"passed_time":0.4252230421,"remaining_time":0.5368200396},
{"learn":[4.060815619],"iteration":442,"passed_time":0.4258260576,"remaining_time":0.5354065781},
{"learn":[4.056407489],"iteration":443,"passed_time":0.4264392473,"remaining_time":0.5340095078},
{"learn":[4.05238936],"iteration":444,"passed_time":0.4270364024,"remaining_time":0.5325959625},
{"learn":[4.049685254],"iteration":445,"passed_time":0.4276492876,"remaining_time":0.5312056173},
{"learn":[4.045162016],"iteration":446,"passed_time":0.4282831708,"remaining_time":0.5298447281},
{"learn":[4.042955482],"iteration":447,"passed_time":0.4288562376,"remaining_time":0.5284121499},
{"learn":[4.041467663],"iteration":448,"passed_time":0.429532364,"remaining_time":0.527109872},
{"learn":[4.038920476],"iteration":449,"passed_time":0.4301196303,"remaining_time":0.5257017703},
{"learn":[4.036694383],"iteration":450,"passed_time":0.4307951282,"remaining_time":0.5244047126},
{"learn":[4.034999007],"iteration":451,"passed_time":0.431465524,"remaining_time":0.5231042194},
{"learn":[4.031928018],"iteration":452,"passed_time":0.4320078184,"remaining_time":0.5216518249},
{"learn":[4.028718143],"iteration":453,"passed_time":0.4326236682,"remaining_time":0.5202919006},
{"learn":[4.027401978],"iteration":454,"passed_time":0.433217112,"remaining_time":0.5189084089},
{"learn":[4.025930598],"iteration":455,"passed_time":0.4338093943,"remaining_time":0.5175269967},
{"learn":[4.021074523],"iteration":456,"passed_time":0.4344719676,"remaining_time":0.5162325566},
{"learn":[4.020268486],"iteration":457,"passed_time":0.435127702,"remaining_time":0.5149327828},
{"learn":[4.017986361],"iteration":458,"passed_time":0.4358138336,"remaining_time":0.5136716427},
{"learn":[4.014814804],"iteration":459,"passed_time":0.4364040734,"remaining_time":0.512300434},
{"learn":[4.009704796],"iteration":460,"passed_time":0.4369911,"remaining_time":0.5109288566},
{"learn":[4.008440457],"iteration":461,"passed_time":0.4376337282,"remaining_time":0.5096254238},
{"learn":[4.004854849],"iteration":462,"passed_time":0.4383703087,"remaining_time":0.5084338138},
{"learn":[4.000898028],"iteration":463,"passed_time":0.4389721104,"remaining_time":0.5070884723},
{"learn":[3.996617985],"iteration":464,"passed_time":0.4396504137,"remaining_time":0.5058343469},
{"learn":[3.995443319],"iteration":465,"passed_time":0.4402771403,"remaining_time":0.50452359},
{"learn":[3.990771995],"iteration":466,"passed_time":0.4408740109,"remaining_time":0.503181687},
{"learn":[3.989249359],"iteration":467,"passed_time":0.4415199691,"remaining_time":0.5018987683},
{"learn":[3.986599538],"iteration":468,"passed_time":0.4421479843,"remaining_time":0.5005982509},
{"learn":[3.985628919],"iteration":469,"passed_time":0.4427855912,"remaining_time":0.4993114114},
{"learn":[3.985086112],"iteration":470,"passed_time":0.4434584753,"remaining_time":0.4980669499},
{"learn":[3.98466839],"iteration":471,"passed_time":0.4442446367,"remaining_time":0.4969516275},
{"learn":[3.984233894],"iteration":472,"passed_time":0.4449106264,"remaining_time":0.4957038058},
{"learn":[3.981855845],"iteration":473,"passed_time":0.4455717235,"remaining_time":0.4944530096},
{"learn":[3.978684264],"iteration":474,"passed_time":0.4461876166,"remaining_time":0.4931547341},
{"learn":[3.974361269],"iteration":475,"passed_time":0.4468223036,"remaining_time":0.4918800149},
{"learn":[3.972074049],"iteration":476,"passed_time":0.4473705201,"remaining_time":0.4905131698},
{"learn":[3.97191982],"iteration":477,"passed_time":0.4479379275,"remaining_time":0.4891707075},
{"learn":[3.969616848],"iteration":478,"passed_time":0.4486568787,"remaining_time":0.4879963127},
{"learn":[3.968533527],"iteration":479,"passed_time":0.4492348068,"remaining_time":0.4866710407},
{"learn":[3.967568753],"iteration":480,"passed_time":0.4498096274,"remaining_time":0.4853455231},
{"learn":[3.966232553],"iteration":481,"passed_time":0.4504591166,"remaining_time":0.484103366},
{"learn":[3.961522393],"iteration":482,"passed_time":0.4511024663,"remaining_time":0.4828570913},
{"learn":[3.955829553],"iteration":483,"passed_time":0.4517558485,"remaining_time":0.4816240037},
{"learn":[3.954248095],"iteration":484,"passed_time":0.4525667522,"remaining_time":0.4805605719},
{"learn":[3.951922606],"iteration":485,"passed_time":0.4532264443,"remaining_time":0.4793382559},
{"learn":[3.94978202],"iteration":486,"passed_time":0.4538721567,"remaining_time":0.4781035244},
{"learn":[3.949518999],"iteration":487,"passed_time":0.4544076433,"remaining_time":0.4767555602},
{"learn":[3.945431216],"iteration":488,"passed_time":0.4549510096,"remaining_time":0.4754191531},
{"learn":[3.943249086],"iteration":489,"passed_time":0.4555581592,"remaining_time":0.4741523698},
{"learn":[3.941981548],"iteration":490,"passed_time":0.4561613578,"remaining_time":0.4728841774},
{"learn":[3.936600517],"iteration":491,"passed_time":0.4566891705,"remaining_time":0.4715408508},
{"learn":[3.934476885],"iteration":492,"passed_time":0.4573155188,"remaining_time":0.4703021663},
{"learn":[3.93045798],"iteration":493,"passed_time":0.4579746835,"remaining_time":0.4690995746},
{"learn":[3.925977375],"iteration":494,"passed_time":0.4586768312,"remaining_time":0.4679430298},
{"learn":[3.92457993],"iteration":495,"passed_time":0.4592907722,"remaining_time":0.4666986878},
{"learn":[3.919849146],"iteration":496,"passed_time":0.4599563055,"remaining_time":0.4655090979},
{"learn":[3.919681964],"iteration":497,"passed_time":0.460556655,"remaining_time":0.4642559053},
{"learn":[3.917633027],"iteration":498,"passed_time":0.4612403282,"remaining_time":0.4630889868},
{"learn":[3.916616419],"iteration":499,"passed_time":0.4619374859,"remaining_time":0.4619374859},
{"learn":[3.912896166],"iteration":500,"passed_time":0.4626503951,"remaining_time":0.4608034874},
{"learn":[3.912769674],"iteration":501,"passed_time":0.4633520695,"remaining_time":0.4596600212},
{"learn":[3.909373788],"iteration":502,"passed_time":0.4640393499,"remaining_time":0.4585040893},
{"learn":[3.906706036],"iteration":503,"passed_time":0.4648277993,"remaining_time":0.4574495803},
{"learn":[3.903895664],"iteration":504,"passed_time":0.4654954614,"remaining_time":0.4562777294},
{"learn":[3.902982967],"iteration":505,"passed_time":0.4661625563,"remaining_time":0.4551073178},
{"learn":[3.900905528],"iteration":506,"passed_time":0.4668391498,"remaining_time":0.4539481279},
{"learn":[3.897463465],"iteration":507,"passed_time":0.467416044,"remaining_time":0.4526942788},
{"learn":[3.895918033],"iteration":508,"passed_time":0.4680748075,"remaining_time":0.4515220638},
{"learn":[3.893921936],"iteration":509,"passed_time":0.468715109,"remaining_time":0.4503341244},
{"learn":[3.890237934],"iteration":510,"passed_time":0.4694302458,"remaining_time":0.4492199416},
{"learn":[3.887311613],"iteration":511,"passed_time":0.4700560947,"remaining_time":0.4480222153},
{"learn":[3.884869735],"iteration":512,"passed_time":0.4707318642,"remaining_time":0.4468741089},
{"learn":[3.882101231],"iteration":513,"passed_time":0.471405256,"remaining_time":0.4457255923},
{"learn":[3.88060368],"iteration":514,"passed_time":0.4721250094,"remaining_time":0.4446225817},
{"learn":[3.877726076],"iteration":515,"passed_time":0.4728158786,"remaining_time":0.4434939637},
{"learn":[3.874938145],"iteration":516,"passed_time":0.4734879149,"remaining_time":0.4423494446},
{"learn":[3.874340833],"iteration":517,"passed_time":0.4740950879,"remaining_time":0.4411463945},
{"learn":[3.873105224],"iteration":518,"passed_time":0.4748523184,"remaining_time":0.4400847112},
{"learn":[3.869800236],"iteration":519,"passed_time":0.4754557723,"remaining_time":0.4388822514},
{"learn":[3.867932518],"iteration":520,"passed_time":0.476118256,"remaining_time":0.437736362},
{"learn":[3.866666962],"iteration":521,"passed_time":0.4768163561,"remaining_time":0.4366249391},
{"learn":[3.865527652],"iteration":522,"passed_time":0.4774956263,"remaining_time":0.435497923},
{"learn":[3.861900081],"iteration":523,"passed_time":0.4781408095,"remaining_time":0.4343416514},
{"learn":[3.858502887],"iteration":524,"passed_time":0.4788431471,"remaining_time":0.4332390379},
{"learn":[3.858335097],"iteration":525,"passed_time":0.4795191096,"remaining_time":0.4321141786},
{"learn":[3.855719306],"iteration":526,"passed_time":0.4802725655,"remaining_time":0.4310605759},
{"learn":[3.855137428],"iteration":527,"passed_time":0.4810493156,"remaining_time":0.4300289336},
{"learn":[3.851985706],"iteration":528,"passed_time":0.4818356133,"remaining_time":0.4290067559},
{"learn":[3.851051809],"iteration":529,"passed_time":0.482682652,"remaining_time":0.4280393329},
{"learn":[3.850679146],"iteration":530,"passed_time":0.4834837608,"remaining_time":0.4270317962},
{"learn":[3.848179484],"iteration":531,"passed_time":0.4841742876,"remaining_time":0.4259277568},
{"learn":[3.844551071],"iteration":532,"passed_time":0.4850124653,"remaining_time":0.4249546366},
{"learn":[3.841604794],"iteration":533,"passed_time":0.4857597802,"remaining_time":0.4239027295},
{"learn":[3.83969656],"iteration":534,"passed_time":0.4864807279,"remaining_time":0.4228290439},
{"learn":[3.836811463],"iteration":535,"passed_time":0.4872096686,"remaining_time":0.4217635937},
{"learn":[3.834182551],"iteration":536,"passed_time":0.4878862246,"remaining_time":0.4206542309},
{"learn":[3.828012842],"iteration":537,"passed_time":0.4885913366,"remaining_time":0.4195709991},
{"learn":[3.826636176],"iteration":538,"passed_time":0.4892265344,"remaining_time":0.4184293736},
{"learn":[3.826189798],"iteration":539,"passed_time":0.4899295548,"remaining_time":0.4173473985},
{"learn":[3.824104738],"iteration":540,"passed_time":0.4906916547,"remaining_time":0.4163169492},
{"learn":[3.82300218],"iteration":541,"passed_time":0.4914265744,"remaining_time":0.4152645223},
{"learn":[3.817146402],"iteration":542,"passed_time":0.4920934143,"remaining_time":0.4141559675},
{"learn":[3.814638044],"iteration":543,"passed_time":0.4927402119,"remaining_time":0.4130322365},
{"learn":[3.812979573],"iteration":544,"passed_time":0.4933881817,"remaining_time":0.4119112343},
{"learn":[3.811938825],"iteration":545,"passed_time":0.4940550836,"remaining_time":0.4108077069},
{"learn":[3.811479418],"iteration":546,"passed_time":0.4947426118,"remaining_time":0.4097228576},
{"learn":[3.80742981],"iteration":547,"passed_time":0.4953691588,"remaining_time":0.4085891602},
{"learn":[3.805097043],"iteration":548,"passed_time":0.4960143293,"remaining_time":0.4074726093},
{"learn":[3.801577232],"iteration":549,"passed_time":0.4967939882,"remaining_time":0.4064678085},
{"learn":[3.799762083],"iteration":550,"passed_time":0.4974819103,"remaining_time":0.4053890703},
{"learn":[3.796393455],"iteration":551,"passed_time":0.4981308646,"remaining_time":0.404280122},
{"learn":[3.793486459],"iteration":552,"passed_time":0.4987640666,"remaining_time":0.4031601045},
{"learn":[3.792006091],"iteration":553,"passed_time":0.4993959062,"remaining_time":0.4020407476},
{"learn":[3.78932128],"iteration":554,"passed_time":0.5000173797,"remaining_time":0.400914836},
{"learn":[3.787581812],"iteration":555,"passed_time":0.5005683016,"remaining_time":0.3997343991},
{"learn":[3.785308865],"iteration":556,"passed_time":0.5011271172,"remaining_time":0.3985625008},
{"learn":[3.78465475],"iteration":557,"passed_time":0.5016782577,"remaining_time":0.3973867203},
{"learn":[3.780498869],"iteration":558,"passed_time":0.5022702716,"remaining_time":0.39624542},
{"learn":[3.778734909],"iteration":559,"passed_time":0.5029117752,"remaining_time":0.3951449662},
{"learn":[3.778652349],"iteration":560,"passed_time":0.5035854041,"remaining_time":0.3940712877},
{"learn":[3.777928006],"iteration":561,"passed_time":0.5042461519,"remaining_time":0.3929889938},
{"learn":[3.776131406],"iteration":562,"passed_time":0.5049235404,"remaining_time":0.3919211139},
{"learn":[3.772925617],"iteration":563,"passed_time":0.5054855094,"remaining_time":0.3907653938},
{"learn":[3.7727745],"iteration":564,"passed_time":0.5060812194,"remaining_time":0.389637753},
{"learn":[3.771763073],"iteration":565,"passed_time":0.5066611456,"remaining_time":0.3884998891},
{"learn":[3.768738162],"iteration":566,"passed_time":0.5073073746,"remaining_time":0.3874146265},
{"learn":[3.767220794],"iteration":567,"passed_time":0.507871935,"remaining_time":0.3862687956},
{"learn":[3.766691102],"iteration":568,"passed_time":0.5084485841,"remaining_time":0.3851341648},
{"learn":[3.766259335],"iteration":569,"passed_time":0.5090476098,"remaining_time":0.3840183723},
{"learn":[3.76116362],"iteration":570,"passed_time":0.5097098932,"remaining_time":0.3829519163},
{"learn":[3.758633056],"iteration":571,"passed_time":0.5103230311,"remaining_time":0.3818501002},
{"learn":[3.754603809],"iteration":572,"passed_time":0.5109560363,"remaining_time":0.3807647949},
{"learn":[3.754070549],"iteration":573,"passed_time":0.5115886268,"remaining_time":0.3796807579},
{"learn":[3.750534319],"iteration":574,"passed_time":0.5122668037,"remaining_time":0.3786319854},
{"learn":[3.746491516],"iteration":575,"passed_time":0.5129473273,"remaining_time":0.377586227},
{"learn":[3.744210544],"iteration":576,"passed_time":0.5135028145,"remaining_time":0.3764500702},
{"learn":[3.742929991],"iteration":577,"passed_time":0.5141214693,"remaining_time":0.3753620416},
{"learn":[3.740402992],"iteration":578,"passed_time":0.5147349105,"remaining_time":0.3742718434},
{"learn":[3.739644243],"iteration":579,"passed_time":0.5153258096,"remaining_time":0.3731669656},
{"learn":[3.737529404],"iteration":580,"passed_time":0.5159756971,"remaining_time":0.3721063978},
{"learn":[3.737196923],"iteration":581,"passed_time":0.5165970206,"remaining_time":0.3710267261},
{"learn":[3.733954464],"iteration":582,"passed_time":0.5172358946,"remaining_time":0.3699611802},
{"learn":[3.731608623],"iteration":583,"passed_time":0.5178885549,"remaining_time":0.3689069158},
{"learn":[3.729843952],"iteration":584,"passed_time":0.5184210964,"remaining_time":0.367768812},
{"learn":[3.727223798],"iteration":585,"passed_time":0.5189606368,"remaining_time":0.3666377195},
{"learn":[3.725351667],"iteration":586,"passed_time":0.5197172477,"remaining_time":0.3656613685},
{"learn":[3.725026912],"iteration":587,"passed_time":0.5202739362,"remaining_time":0.3645456832},
{"learn":[3.721974565],"iteration":588,"passed_time":0.5208443837,"remaining_time":0.363441497},
{"learn":[3.720269493],"iteration":589,"passed_time":0.5214742435,"remaining_time":0.3623804065},
{"learn":[3.718907466],"iteration":590,"passed_time":0.5221935174,"remaining_time":0.3613826542},
{"learn":[3.715602912],"iteration":591,"passed_time":0.5229002994,"remaining_time":0.3603772334},
{"learn":[3.714463059],"iteration":592,"passed_time":0.5235129862,"remaining_time":0.3593082384},
{"learn":[3.710802077],"iteration":593,"passed_time":0.5241485172,"remaining_time":0.3582563939},
{"learn":[3.708032435],"iteration":594,"passed_time":0.5247304443,"remaining_time":0.3571694621},
{"learn":[3.703788939],"iteration":595,"passed_time":0.5253174777,"remaining_time":0.3560876863},
{"learn":[3.702500944],"iteration":596,"passed_time":0.5259352537,"remaining_time":0.3550283204},
{"learn":[3.698196925],"iteration":597,"passed_time":0.5265183105,"remaining_time":0.3539470917},
{"learn":[3.69658891],"iteration":598,"passed_time":0.5271179849,"remaining_time":0.352878651},
{"learn":[3.696124066],"iteration":599,"passed_time":0.5276338141,"remaining_time":0.3517558761},
{"learn":[3.693537052],"iteration":600,"passed_time":0.5282204394,"remaining_time":0.350682122},
{"learn":[3.691343275],"iteration":601,"passed_time":0.5287688094,"remaining_time":0.3495846946},
{"learn":[3.690973831],"iteration":602,"passed_time":0.5294970776,"remaining_time":0.3486075287},
{"learn":[3.686151073],"iteration":603,"passed_time":0.530242667,"remaining_time":0.3476425433},
{"learn":[3.683921982],"iteration":604,"passed_time":0.5307769953,"remaining_time":0.3465403523},
{"learn":[3.679975271],"iteration":605,"passed_time":0.5313841564,"remaining_time":0.3454873888},
{"learn":[3.674047638],"iteration":606,"passed_time":0.5320054566,"remaining_time":0.3444450485},
{"learn":[3.673151794],"iteration":607,"passed_time":0.532594711,"remaining_time":0.3433834321},
{"learn":[3.670953108],"iteration":608,"passed_time":0.5331451228,"remaining_time":0.3422984286},
{"learn":[3.6703947],"iteration":609,"passed_time":0.5337297879,"remaining_time":0.3412370775},
{"learn":[3.668433805],"iteration":610,"passed_time":0.5343303434,"remaining_time":0.3401874036},
{"learn":[3.668304956],"iteration":611,"passed_time":0.5349468297,"remaining_time":0.3391492973},
{"learn":[3.667880012],"iteration":612,"passed_time":0.5355509442,"remaining_time":0.338104756},
{"learn":[3.667282264],"iteration":613,"passed_time":0.5361944314,"remaining_time":0.3370864015},
{"learn":[3.664611483],"iteration":614,"passed_time":0.5368319069,"remaining_time":0.3360655027},
{"learn":[3.662543394],"iteration":615,"passed_time":0.5374068463,"remaining_time":0.3350068652},
{"learn":[3.659041959],"iteration":616,"passed_time":0.5380072869,"remaining_time":0.3339656254},
{"learn":[3.656868545],"iteration":617,"passed_time":0.5385348994,"remaining_time":0.3328807954},
{"learn":[3.654785614],"iteration":618,"passed_time":0.5391328705,"remaining_time":0.3318410722},
{"learn":[3.654566096],"iteration":619,"passed_time":0.5396554413,"remaining_time":0.3307565608},
{"learn":[3.651007045],"iteration":620,"passed_time":0.5402880838,"remaining_time":0.3297410367},
{"learn":[3.648921786],"iteration":621,"passed_time":0.5409423792,"remaining_time":0.3287399025},
{"learn":[3.647655706],"iteration":622,"passed_time":0.5415184057,"remaining_time":0.3276925184},
{"learn":[3.647241144],"iteration":623,"passed_time":0.5421008547,"remaining_time":0.326650515},
{"learn":[3.644195689],"iteration":624,"passed_time":0.5427733137,"remaining_time":0.3256639882},
{"learn":[3.642632246],"iteration":625,"passed_time":0.5433786441,"remaining_time":0.3246383592},
{"learn":[3.642523322],"iteration":626,"passed_time":0.5439355159,"remaining_time":0.3235852431},
{"learn":[3.641494659],"iteration":627,"passed_time":0.5445691012,"remaining_time":0.3225791491},
{"learn":[3.63976496],"iteration":628,"passed_time":0.5451700623,"remaining_time":0.321554997},
{"learn":[3.637945652],"iteration":629,"passed_time":0.5458407258,"remaining_time":0.3205731247},
{"learn":[3.636233667],"iteration":630,"passed_time":0.5464156463,"remaining_time":0.3195362496},
{"learn":[3.635304404],"iteration":631,"passed_time":0.5470135585,"remaining_time":0.318514224},
{"learn":[3.632234951],"iteration":632,"passed_time":0.5475718897,"remaining_time":0.3174705901},
{"learn":[3.631630987],"iteration":633,"passed_time":0.54820007,"remaining_time":0.3164688101},
{"learn":[3.630301009],"iteration":634,"passed_time":0.5487662329,"remaining_time":0.3154325591},
{"learn":[3.629077964],"iteration":635,"passed_time":0.5493839924,"remaining_time":0.3144273164},
{"learn":[3.628004522],"iteration":636,"passed_time":0.5500081753,"remaining_time":0.3134269507},
{"learn":[3.625062876],"iteration":637,"passed_time":0.5506617661,"remaining_time":0.3124444503},
{"learn":[3.624917986],"iteration":638,"passed_time":0.5511983728,"remaining_time":0.3113968898},
{"learn":[3.622887087],"iteration":639,"passed_time":0.5517948042,"remaining_time":0.3103845774},
{"learn":[3.621220865],"iteration":640,"passed_time":0.5523454243,"remaining_time":0.3093479053},
{"learn":[3.621143844],"iteration":641,"passed_time":0.5528660681,"remaining_time":0.3082960318},
{"learn":[3.620822821],"iteration":642,"passed_time":0.5534133407,"remaining_time":0.3072605951},
{"learn":[3.619202826],"iteration":643,"passed_time":0.5540131736,"remaining_time":0.3062557295},
{"learn":[3.618204882],"iteration":644,"passed_time":0.5546697628,"remaining_time":0.3052833578},
{"learn":[3.614259666],"iteration":645,"passed_time":0.5553243408,"remaining_time":0.3043108617},
{"learn":[3.613415661],"iteration":646,"passed_time":0.5559269125,"remaining_time":0.3033109739},
{"learn":[3.611096773],"iteration":647,"passed_time":0.5566221184,"remaining_time":0.3023626322},
{"learn":[3.610820695],"iteration":648,"passed_time":0.5572311594,"remaining_time":0.3013684699},
{"learn":[3.609290065],"iteration":649,"passed_time":0.5577979886,"remaining_time":0.3003527631},
{"learn":[3.60897947],"iteration":650,"passed_time":0.5583390676,"remaining_time":0.2993246307},
{"learn":[3.606570702],"iteration":651,"passed_time":0.5588715237,"remaining_time":0.29829339},
{"learn":[3.606292637],"iteration":652,"passed_time":0.5595500361,"remaining_time":0.2973412903},
{"learn":[3.602753838],"iteration":653,"passed_time":0.5600862389,"remaining_time":0.296314738},
{"learn":[3.599755869],"iteration":654,"passed_time":0.5606943611,"remaining_time":0.2953275643},
{"learn":[3.599509575],"iteration":655,"passed_time":0.5612181182,"remaining_time":0.2942973059},
{"learn":[3.595337722],"iteration":656,"passed_time":0.5617650109,"remaining_time":0.2932806678},
{"learn":[3.595168561],"iteration":657,"passed_time":0.5623000411,"remaining_time":0.2922592919},
{"learn":[3.59290559],"iteration":658,"passed_time":0.5629828354,"remaining_time":0.2913158526},
{"learn":[3.592015928],"iteration":659,"passed_time":0.5636544424,"remaining_time":0.29036744},
{"learn":[3.590680403],"iteration":660,"passed_time":0.5643801224,"remaining_time":0.2894475968},
{"learn":[3.590361532],"iteration":661,"passed_time":0.5649191516,"remaining_time":0.2884330411},
{"learn":[3.589069739],"iteration":662,"passed_time":0.565487171,"remaining_time":0.2874346555},
{"learn":[3.585010186],"iteration":663,"passed_time":0.5660693362,"remaining_time":0.2864447244},
{"learn":[3.582997552],"iteration":664,"passed_time":0.5666364101,"remaining_time":0.2854484171},
{"learn":[3.582119256],"iteration":665,"passed_time":0.5671488179,"remaining_time":0.2844259837},
{"learn":[3.579019356],"iteration":666,"passed_time":0.5677324992,"remaining_time":0.283440663},
{"learn":[3.57719559],"iteration":667,"passed_time":0.5682625007,"remaining_time":0.2824298656},
{"learn":[3.574050046],"iteration":668,"passed_time":0.5688350211,"remaining_time":0.2814415426},
{"learn":[3.572204518],"iteration":669,"passed_time":0.5694576879,"remaining_time":0.2804791597},
{"learn":[3.569508025],"iteration":670,"passed_time":0.5701115586,"remaining_time":0.2795330891},
{"learn":[3.566268704],"iteration":671,"passed_time":0.5707484896,"remaining_time":0.2785796199},
{"learn":[3.562564052],"iteration":672,"passed_time":0.5714402717,"remaining_time":0.2776537427},
{"learn":[3.561173586],"iteration":673,"passed_time":0.5721327232,"remaining_time":0.2767288839},
{"learn":[3.559551904],"iteration":674,"passed_time":0.5727242439,"remaining_time":0.2757561174},
{"learn":[3.558593054],"iteration":675,"passed_time":0.5733438166,"remaining_time":0.2747979239},
{"learn":[3.555647008],"iteration":676,"passed_time":0.5739563939,"remaining_time":0.2738373933},
{"learn":[3.553100059],"iteration":677,"passed_time":0.5745041375,"remaining_time":0.2728470977},
{"learn":[3.55085578],"iteration":678,"passed_time":0.5751249057,"remaining_time":0.2718926285},
{"learn":[3.550737965],"iteration":679,"passed_time":0.5756851669,"remaining_time":0.2709106668},
{"learn":[3.549408772],"iteration":680,"passed_time":0.576205988,"remaining_time":0.2699114687},
{"learn":[3.547390589],"iteration":681,"passed_time":0.5768287478,"remaining_time":0.268961205},
{"learn":[3.54723575],"iteration":682,"passed_time":0.5775496879,"remaining_time":0.2680574686},
{"learn":[3.543988891],"iteration":683,"passed_time":0.5781842087,"remaining_time":0.2671143421},
{"learn":[3.543868508],"iteration":684,"passed_time":0.5787860379,"remaining_time":0.2661570831},
{"learn":[3.542752124],"iteration":685,"passed_time":0.5792998288,"remaining_time":0.265160563},
{"learn":[3.541334315],"iteration":686,"passed_time":0.579916008,"remaining_time":0.2642120968},
{"learn":[3.540208266],"iteration":687,"passed_time":0.5804137035,"remaining_time":0.2632108655},
{"learn":[3.537730983],"iteration":688,"passed_time":0.5809073476,"remaining_time":0.2622092672},
{"learn":[3.53419867],"iteration":689,"passed_time":0.581548868,"remaining_time":0.2612755784},
{"learn":[3.532628335],"iteration":690,"passed_time":0.5821634144,"remaining_time":0.260330673},
{"learn":[3.532204987],"iteration":691,"passed_time":0.5827360963,"remaining_time":0.2593680891},
{"learn":[3.530618147],"iteration":692,"passed_time":0.5832677832,"remaining_time":0.2583884696},
{"learn":[3.528909306],"iteration":693,"passed_time":0.584208899,"remaining_time":0.2575906673},
{"learn":[3.526700678],"iteration":694,"passed_time":0.5849297943,"remaining_time":0.256695809},
{"learn":[3.526439574],"iteration":695,"passed_time":0.5855905107,"remaining_time":0.2557751656},
{"learn":[3.525784216],"iteration":696,"passed_time":0.5862112617,"remaining_time":0.2548378942},
{"learn":[3.524112693],"iteration":697,"passed_time":0.5868889278,"remaining_time":0.253926155},
{"learn":[3.522813541],"iteration":698,"passed_time":0.5874758659,"remaining_time":0.2529760166},
{"learn":[3.519148203],"iteration":699,"passed_time":0.5880177242,"remaining_time":0.2520075961},
{"learn":[3.517236747],"iteration":700,"passed_time":0.5885745328,"remaining_time":0.2510467694},
{"learn":[3.515603888],"iteration":701,"passed_time":0.5892267367,"remaining_time":0.2501275891},
{"learn":[3.51263524],"iteration":702,"passed_time":0.5898691455,"remaining_time":0.2492050302},
{"learn":[3.51123442],"iteration":703,"passed_time":0.5905484299,"remaining_time":0.2482987717},
{"learn":[3.50828027],"iteration":704,"passed_time":0.5911256645,"remaining_time":0.2473504554},
{"learn":[3.508265537],"iteration":705,"passed_time":0.5915729731,"remaining_time":0.2463490851},
{"learn":[3.506774876],"iteration":706,"passed_time":0.592134485,"remaining_time":0.2453966112},
{"learn":[3.50552068],"iteration":707,"passed_time":0.5926861222,"remaining_time":0.244441169},
{"learn":[3.501973993],"iteration":708,"passed_time":0.5932897327,"remaining_time":0.2435081978},
{"learn":[3.498880354],"iteration":709,"passed_time":0.5939642293,"remaining_time":0.2426051078},
{"learn":[3.497370959],"iteration":710,"passed_time":0.5945367302,"remaining_time":0.2416612026},
{"learn":[3.496050455],"iteration":711,"passed_time":0.5950492467,"remaining_time":0.2406940773},
{"learn":[3.495630067],"iteration":712,"passed_time":0.5956024523,"remaining_time":0.2397446056},
{"learn":[3.49550669],"iteration":713,"passed_time":0.5962176497,"remaining_time":0.2388210754},
{"learn":[3.493652375],"iteration":714,"passed_time":0.5968212468,"remaining_time":0.2378937837},
{"learn":[3.491915684],"iteration":715,"passed_time":0.5974780505,"remaining_time":0.2369885005},
{"learn":[3.490303956],"iteration":716,"passed_time":0.5981521768,"remaining_time":0.2360907476},
{"learn":[3.488363853],"iteration":717,"passed_time":0.5987967358,"remaining_time":0.2351820048},
{"learn":[3.485483936],"iteration":718,"passed_time":0.5994049691,"remaining_time":0.2342598002},
{"learn":[3.483763466],"iteration":719,"passed_time":0.6000059577,"remaining_time":0.2333356502},
{"learn":[3.481642352],"iteration":720,"passed_time":0.6005693613,"remaining_time":0.2323978527},
{"learn":[3.479826119],"iteration":721,"passed_time":0.6011388159,"remaining_time":0.2314634222},
{"learn":[3.478588728],"iteration":722,"passed_time":0.6016974327,"remaining_time":0.2305258491},
{"learn":[3.475390887],"iteration":723,"passed_time":0.6022117854,"remaining_time":0.2295724486},
{"learn":[3.472636852],"iteration":724,"passed_time":0.6027989563,"remaining_time":0.22864788},
{"learn":[3.47061883],"iteration":725,"passed_time":0.6034526881,"remaining_time":0.2277493616},
{"learn":[3.46953149],"iteration":726,"passed_time":0.6041015198,"remaining_time":0.2268496766},
{"learn":[3.467217162],"iteration":727,"passed_time":0.6047268499,"remaining_time":0.2259419},
{"learn":[3.465686216],"iteration":728,"passed_time":0.6053268154,"remaining_time":0.2250254691},
{"learn":[3.462631216],"iteration":729,"passed_time":0.6059518586,"remaining_time":0.2241191806},
{"learn":[3.461451053],"iteration":730,"passed_time":0.6065514626,"remaining_time":0.2232043002},
{"learn":[3.458950469],"iteration":731,"passed_time":0.6070967048,"remaining_time":0.2222703783},
{"learn":[3.458072145],"iteration":732,"passed_time":0.6076252068,"remaining_time":0.2213314191},
{"learn":[3.454364268],"iteration":733,"passed_time":0.608230384,"remaining_time":0.2204213653},
{"learn":[3.453243406],"iteration":734,"passed_time":0.6088474297,"remaining_time":0.2195164202},
{"learn":[3.453017963],"iteration":735,"passed_time":0.6094277473,"remaining_time":0.2185990833},
{"learn":[3.45201581],"iteration":736,"passed_time":0.6100103893,"remaining_time":0.2176834904},
{"learn":[3.449510107],"iteration":737,"passed_time":0.6107426964,"remaining_time":0.2168219329},
{"learn":[3.447189189],"iteration":738,"passed_time":0.6114282934,"remaining_time":0.2159442281},
{"learn":[3.446423605],"iteration":739,"passed_time":0.6120201116,"remaining_time":0.2150340933},
{"learn":[3.445531987],"iteration":740,"passed_time":0.6126398194,"remaining_time":0.2141345658},
{"learn":[3.445328199],"iteration":741,"passed_time":0.6131923198,"remaining_time":0.2132124239},
{"learn":[3.443327544],"iteration":742,"passed_time":0.6138075657,"remaining_time":0.2123129803},
{"learn":[3.441475798],"iteration":743,"passed_time":0.6145468632,"remaining_time":0.2114569852},
{"learn":[3.439046501],"iteration":744,"passed_time":0.6151124471,"remaining_time":0.2105418443},
{"learn":[3.435899469],"iteration":745,"passed_time":0.6157031808,"remaining_time":0.2096362037},
{"learn":[3.433988352],"iteration":746,"passed_time":0.6162348079,"remaining_time":0.2087113874},
{"learn":[3.433413263],"iteration":747,"passed_time":0.6168596563,"remaining_time":0.2078190286},
{"learn":[3.429944699],"iteration":748,"passed_time":0.6174972758,"remaining_time":0.2069316638},
{"learn":[3.429291634],"iteration":749,"passed_time":0.6182009525,"remaining_time":0.2060669842},
{"learn":[3.429175603],"iteration":750,"passed_time":0.6187855192,"remaining_time":0.2051632414},
{"learn":[3.428780323],"iteration":751,"passed_time":0.619292271,"remaining_time":0.2042346851},
{"learn":[3.423893341],"iteration":752,"passed_time":0.6198387401,"remaining_time":0.2033202773},
{"learn":[3.421024316],"iteration":753,"passed_time":0.6203783261,"remaining_time":0.2024045998},
{"learn":[3.420969872],"iteration":754,"passed_time":0.6208655101,"remaining_time":0.2014729139},
{"learn":[3.419544785],"iteration":755,"passed_time":0.6214562542,"remaining_time":0.2005758281},
{"learn":[3.417057977],"iteration":756,"passed_time":0.6220191806,"remaining_time":0.199670622},
{"learn":[3.415160245],"iteration":757,"passed_time":0.6226795053,"remaining_time":0.1987974146},
{"learn":[3.412854597],"iteration":758,"passed_time":0.6232871585,"remaining_time":0.1979080437},
{"learn":[3.410926347],"iteration":759,"passed_time":0.6240008006,"remaining_time":0.1970528844},
{"learn":[3.408963843],"iteration":760,"passed_time":0.6246702395,"remaining_time":0.1961842145},
{"learn":[3.407629634],"iteration":761,"passed_time":0.6254545187,"remaining_time":0.1953519363},
{"learn":[3.404384724],"iteration":762,"passed_time":0.6261714847,"remaining_time":0.1944988753},
{"learn":[3.403041656],"iteration":763,"passed_time":0.6268617122,"remaining_time":0.1936379111},
{"learn":[3.401101731],"iteration":764,"passed_time":0.6275679121,"remaining_time":0.1927822998},
{"learn":[3.400890668],"iteration":765,"passed_time":0.6281896855,"remaining_time":0.1919012877},
{"learn":[3.399289941],"iteration":766,"passed_time":0.6287528608,"remaining_time":0.1910031507},
{"learn":[3.399202366],"iteration":767,"passed_time":0.629283431,"remaining_time":0.1900960364},
{"learn":[3.397447845],"iteration":768,"passed_time":0.6298472186,"remaining_time":0.1891998797},
{"learn":[3.394655341],"iteration":769,"passed_time":0.63040768,"remaining_time":0.1883035927},
{"learn":[3.393228229],"iteration":770,"passed_time":0.6311270099,"remaining_time":0.1874553635},
{"learn":[3.389691197],"iteration":771,"passed_time":0.631714409,"remaining_time":0.1865685042},
{"learn":[3.389626772],"iteration":772,"passed_time":0.6322836289,"remaining_time":0.1856770812},
{"learn":[3.388480222],"iteration":773,"passed_time":0.6328521871,"remaining_time":0.1847862975},
{"learn":[3.388215066],"iteration":774,"passed_time":0.6333875252,"remaining_time":0.1838867009},
{"learn":[3.386324358],"iteration":775,"passed_time":0.6339957715,"remaining_time":0.1830090887},
{"learn":[3.383913061],"iteration":776,"passed_time":0.6346170387,"remaining_time":0.1821359069},
{"learn":[3.382839768],"iteration":777,"passed_time":0.6352959934,"remaining_time":0.1812798336},
{"learn":[3.381961844],"iteration":778,"passed_time":0.6358693003,"remaining_time":0.1803942431},
{"learn":[3.381521703],"iteration":779,"passed_time":0.6364388587,"remaining_time":0.179508396},
{"learn":[3.380918963],"iteration":780,"passed_time":0.6370268552,"remaining_time":0.1786285292},
{"learn":[3.377139006],"iteration":781,"passed_time":0.6377396986,"remaining_time":0.1777842126},
{"learn":[3.376004372],"iteration":782,"passed_time":0.6383823199,"remaining_time":0.1769207707},
{"learn":[3.373826468],"iteration":783,"passed_time":0.6390972112,"remaining_time":0.1760778031},
{"learn":[3.373546786],"iteration":784,"passed_time":0.6396410619,"remaining_time":0.1751883163},
{"learn":[3.372109181],"iteration":785,"passed_time":0.6402054511,"remaining_time":0.1743053009},
{"learn":[3.370764924],"iteration":786,"passed_time":0.6408054832,"remaining_time":0.1734327419},
{"learn":[3.367833107],"iteration":787,"passed_time":0.6413867995,"remaining_time":0.1725558394},
{"learn":[3.36450404],"iteration":788,"passed_time":0.6419365331,"remaining_time":0.1716712402},
{"learn":[3.361794558],"iteration":789,"passed_time":0.6425129528,"remaining_time":0.1707945824},
{"learn":[3.356880529],"iteration":790,"passed_time":0.643061033,"remaining_time":0.1699111958},
{"learn":[3.353843509],"iteration":791,"passed_time":0.6436959026,"remaining_time":0.1690514492},
{"learn":[3.353640253],"iteration":792,"passed_time":0.6443062387,"remaining_time":0.1681858656},
{"learn":[3.353055088],"iteration":793,"passed_time":0.644972758,"remaining_time":0.1673355014},
{"learn":[3.351415617],"iteration":794,"passed_time":0.6455006561,"remaining_time":0.1664498547},
{"learn":[3.349169061],"iteration":795,"passed_time":0.6461071678,"remaining_time":0.1655852541},
{"learn":[3.346211014],"iteration":796,"passed_time":0.6466580269,"remaining_time":0.164707126},
{"learn":[3.344560452],"iteration":797,"passed_time":0.647195105,"remaining_time":0.1638263298},
{"learn":[3.344445461],"iteration":798,"passed_time":0.6478268135,"remaining_time":0.1629701997},
{"learn":[3.342608898],"iteration":799,"passed_time":0.6485084373,"remaining_time":0.1621271093},
{"learn":[3.339572899],"iteration":800,"passed_time":0.6491641786,"remaining_time":0.1612779919},
{"learn":[3.339309302],"iteration":801,"passed_time":0.6497119099,"remaining_time":0.160402691},
{"learn":[3.33698088],"iteration":802,"passed_time":0.6502790937,"remaining_time":0.1595329782},
{"learn":[3.334746342],"iteration":803,"passed_time":0.6509184992,"remaining_time":0.1586816242},
{"learn":[3.332048511],"iteration":804,"passed_time":0.6516156386,"remaining_time":0.157844782},
{"learn":[3.331932544],"iteration":805,"passed_time":0.6521687849,"remaining_time":0.1569736281},
{"learn":[3.330541133],"iteration":806,"passed_time":0.6528249582,"remaining_time":0.156127902},
{"learn":[3.329124989],"iteration":807,"passed_time":0.6534133162,"remaining_time":0.1552665306},
{"learn":[3.32583918],"iteration":808,"passed_time":0.6539575494,"remaining_time":0.1543954165},
{"learn":[3.325287299],"iteration":809,"passed_time":0.6545262087,"remaining_time":0.1535308391},
{"learn":[3.322745162],"iteration":810,"passed_time":0.6551018208,"remaining_time":0.1526686118},
{"learn":[3.319733662],"iteration":811,"passed_time":0.6556041468,"remaining_time":0.1517901227},
{"learn":[3.318080007],"iteration":812,"passed_time":0.6561956858,"remaining_time":0.150933079},
{"learn":[3.317179538],"iteration":813,"passed_time":0.6568987139,"remaining_time":0.1501021631},
{"learn":[3.315685949],"iteration":814,"passed_time":0.6574824181,"remaining_time":0.1492444753},
{"learn":[3.314944576],"iteration":815,"passed_time":0.6581073308,"remaining_time":0.1483967511},
{"learn":[3.312369052],"iteration":816,"passed_time":0.6588862939,"remaining_time":0.1475840781},
{"learn":[3.312321621],"iteration":817,"passed_time":0.65937397,"remaining_time":0.1467066779},
{"learn":[3.309465776],"iteration":818,"passed_time":0.6599772926,"remaining_time":0.1458557875},
{"learn":[3.308307377],"iteration":819,"passed_time":0.6605735505,"remaining_time":0.1450039501},
{"learn":[3.308076804],"iteration":820,"passed_time":0.6611068602,"remaining_time":0.1441390109},
{"learn":[3.305643326],"iteration":821,"passed_time":0.6617828364,"remaining_time":0.1433057724},
{"learn":[3.304154814],"iteration":822,"passed_time":0.6624567425,"remaining_time":0.1424724708},
{"learn":[3.303076321],"iteration":823,"passed_time":0.6630346354,"remaining_time":0.1416190483},
{"learn":[3.301746372],"iteration":824,"passed_time":0.6636762083,"remaining_time":0.1407798018},
{"learn":[3.301345455],"iteration":825,"passed_time":0.6642729461,"remaining_time":0.1399315891},
{"learn":[3.299181039],"iteration":826,"passed_time":0.6650185875,"remaining_time":0.1391151338},
{"learn":[3.297989357],"iteration":827,"passed_time":0.6656944508,"remaining_time":0.1382843545},
{"learn":[3.294775182],"iteration":828,"passed_time":0.6662310564,"remaining_time":0.1374252239},
{"learn":[3.293840636],"iteration":829,"passed_time":0.6668910896,"remaining_time":0.1365921509},
{"learn":[3.289279397],"iteration":830,"passed_time":0.6674620691,"remaining_time":0.1357413835},
{"learn":[3.286204979],"iteration":831,"passed_time":0.6680431652,"remaining_time":0.1348933314},
{"learn":[3.284833593],"iteration":832,"passed_time":0.6686084646,"remaining_time":0.1340427534},
{"learn":[3.283519914],"iteration":833,"passed_time":0.6691691811,"remaining_time":0.1331919473},
{"learn":[3.282853026],"iteration":834,"passed_time":0.6699075032,"remaining_time":0.1323769318},
{"learn":[3.281944673],"iteration":835,"passed_time":0.670543287,"remaining_time":0.1315419845},
{"learn":[3.279764865],"iteration":836,"passed_time":0.6711291042,"remaining_time":0.1306977825},
{"learn":[3.277468839],"iteration":837,"passed_time":0.6717260675,"remaining_time":0.129856352},
{"learn":[3.277124974],"iteration":838,"passed_time":0.6723191605,"remaining_time":0.1290147614},
{"learn":[3.275636037],"iteration":839,"passed_time":0.6728968137,"remaining_time":0.1281708217},
{"learn":[3.274413635],"iteration":840,"passed_time":0.6734230299,"remaining_time":0.1273177904},
{"learn":[3.272636087],"iteration":841,"passed_time":0.6739357479,"remaining_time":0.1264630026},
{"learn":[3.269644466],"iteration":842,"passed_time":0.6745158824,"remaining_time":0.1256215819},
{"learn":[3.26852083],"iteration":843,"passed_time":0.67511327,"remaining_time":0.1247839693},
{"learn":[3.267820927],"iteration":844,"passed_time":0.6756513594,"remaining_time":0.1239360482},
{"learn":[3.267331099],"iteration":845,"passed_time":0.6761728741,"remaining_time":0.1230858423},
{"learn":[3.267231014],"iteration":846,"passed_time":0.6766672718,"remaining_time":0.1222315143},
{"learn":[3.267158695],"iteration":847,"passed_time":0.6771550578,"remaining_time":0.12137685},
{"learn":[3.264718705],"iteration":848,"passed_time":0.6776748232,"remaining_time":0.1205287377},
{"learn":[3.261678512],"iteration":849,"passed_time":0.6782193765,"remaining_time":0.1196857723},
{"learn":[3.261368381],"iteration":850,"passed_time":0.6788126563,"remaining_time":0.1188520397},
{"learn":[3.260128799],"iteration":851,"passed_time":0.6794520289,"remaining_time":0.1180268783},
{"learn":[3.258972952],"iteration":852,"passed_time":0.6800221682,"remaining_time":0.1171902213},
{"learn":[3.258724846],"iteration":853,"passed_time":0.6805532967,"remaining_time":0.1163475191},
{"learn":[3.25686724],"iteration":854,"passed_time":0.6810698777,"remaining_time":0.1155030787},
{"learn":[3.255750259],"iteration":855,"passed_time":0.681624414,"remaining_time":0.1146657893},
{"learn":[3.254915866],"iteration":856,"passed_time":0.6821307737,"remaining_time":0.1138211209},
{"learn":[3.254348625],"iteration":857,"passed_time":0.6826695563,"remaining_time":0.1129826072},
{"learn":[3.253408514],"iteration":858,"passed_time":0.6832378617,"remaining_time":0.1121496374},
{"learn":[3.253291714],"iteration":859,"passed_time":0.6837754151,"remaining_time":0.1113122769},
{"learn":[3.250186342],"iteration":860,"passed_time":0.6843792355,"remaining_time":0.110486311},
{"learn":[3.249141318],"iteration":861,"passed_time":0.6850779418,"remaining_time":0.109676051},
{"learn":[3.246300388],"iteration":862,"passed_time":0.6858229614,"remaining_time":0.1088734017},
{"learn":[3.245205135],"iteration":863,"passed_time":0.6864667859,"remaining_time":0.108054957},
{"learn":[3.244403535],"iteration":864,"passed_time":0.6870640655,"remaining_time":0.1072296518},
{"learn":[3.244211781],"iteration":865,"passed_time":0.6878712104,"remaining_time":0.1064373466},
{"learn":[3.242286347],"iteration":866,"passed_time":0.6884965466,"remaining_time":0.1056171173},
{"learn":[3.239606746],"iteration":867,"passed_time":0.6890478265,"remaining_time":0.104786075},
{"learn":[3.236773361],"iteration":868,"passed_time":0.689609642,"remaining_time":0.1039572648},
{"learn":[3.234552446],"iteration":869,"passed_time":0.690211148,"remaining_time":0.1031349991},
{"learn":[3.233724647],"iteration":870,"passed_time":0.6907322988,"remaining_time":0.1023013393},
{"learn":[3.230851485],"iteration":871,"passed_time":0.6913251222,"remaining_time":0.101478917},
{"learn":[3.227728941],"iteration":872,"passed_time":0.691942534,"remaining_time":0.1006605977},
{"learn":[3.225787575],"iteration":873,"passed_time":0.6927040385,"remaining_time":0.09986351126},
{"learn":[3.222797487],"iteration":874,"passed_time":0.6934089034,"remaining_time":0.09905841478},
{"learn":[3.22137014],"iteration":875,"passed_time":0.6940536593,"remaining_time":0.09824503853},
{"learn":[3.219701963],"iteration":876,"passed_time":0.6946673639,"remaining_time":0.09742769186},
{"learn":[3.21783327],"iteration":877,"passed_time":0.6952222932,"remaining_time":0.0966026421},
{"learn":[3.217713355],"iteration":878,"passed_time":0.6957829446,"remaining_time":0.09577899464},
{"learn":[3.217666091],"iteration":879,"passed_time":0.6963428768,"remaining_time":0.09495584684},
{"learn":[3.214962005],"iteration":880,"passed_time":0.6969768669,"remaining_time":0.09414329984},
{"learn":[3.214081828],"iteration":881,"passed_time":0.6975383401,"remaining_time":0.09332145593},
{"learn":[3.213358337],"iteration":882,"passed_time":0.6981400597,"remaining_time":0.09250553453},
{"learn":[3.210850401],"iteration":883,"passed_time":0.6988032483,"remaining_time":0.09169816381},
{"learn":[3.207810328],"iteration":884,"passed_time":0.6995565408,"remaining_time":0.09090282733},
{"learn":[3.204935073],"iteration":885,"passed_time":0.7002539202,"remaining_time":0.09010039154},
{"learn":[3.20280198],"iteration":886,"passed_time":0.7009199177,"remaining_time":0.0892941947},
{"learn":[3.200663495],"iteration":887,"passed_time":0.7015525376,"remaining_time":0.08848410384},
{"learn":[3.197301669],"iteration":888,"passed_time":0.7021552249,"remaining_time":0.08767067488},
{"learn":[3.195666943],"iteration":889,"passed_time":0.7028265248,"remaining_time":0.0868661997},
{"learn":[3.193886506],"iteration":890,"passed_time":0.7034278658,"remaining_time":0.08605346506},
{"learn":[3.190601248],"iteration":891,"passed_time":0.7039722108,"remaining_time":0.08523430355},
{"learn":[3.188983797],"iteration":892,"passed_time":0.7045883459,"remaining_time":0.08442435948},
{"learn":[3.187365749],"iteration":893,"passed_time":0.7051331658,"remaining_time":0.08360639326},
{"learn":[3.186160771],"iteration":894,"passed_time":0.7058321547,"remaining_time":0.08280712429},
{"learn":[3.185358981],"iteration":895,"passed_time":0.706495866,"remaining_time":0.08200398444},
{"learn":[3.183832164],"iteration":896,"passed_time":0.7071205677,"remaining_time":0.08119667611},
{"learn":[3.183106966],"iteration":897,"passed_time":0.707750833,"remaining_time":0.08039040642},
{"learn":[3.182838152],"iteration":898,"passed_time":0.7082977662,"remaining_time":0.07957516617},
{"learn":[3.180835453],"iteration":899,"passed_time":0.7089073942,"remaining_time":0.07876748824},
{"learn":[3.179957348],"iteration":900,"passed_time":0.7095411672,"remaining_time":0.07796290294},
{"learn":[3.179752966],"iteration":901,"passed_time":0.710103312,"remaining_time":0.07715091416},
{"learn":[3.178851983],"iteration":902,"passed_time":0.710775259,"remaining_time":0.07635127367},
{"learn":[3.176748586],"iteration":903,"passed_time":0.7113067195,"remaining_time":0.07553699676},
{"learn":[3.172960988],"iteration":904,"passed_time":0.7119023559,"remaining_time":0.07473008156},
{"learn":[3.172794225],"iteration":905,"passed_time":0.7124771498,"remaining_time":0.07392147029},
{"learn":[3.169996507],"iteration":906,"passed_time":0.7130855233,"remaining_time":0.07311681771},
{"learn":[3.16813015],"iteration":907,"passed_time":0.713702366,"remaining_time":0.07231345559},
{"learn":[3.166920871],"iteration":908,"passed_time":0.7143815003,"remaining_time":0.07151673986},
{"learn":[3.16531606],"iteration":909,"passed_time":0.7150674014,"remaining_time":0.07072095179},
{"learn":[3.162035247],"iteration":910,"passed_time":0.7157603377,"remaining_time":0.06992609226},
{"learn":[3.16189467],"iteration":911,"passed_time":0.716506135,"remaining_time":0.06913655689},
{"learn":[3.161008416],"iteration":912,"passed_time":0.7176426991,"remaining_time":0.06838435359},
{"learn":[3.160560787],"iteration":913,"passed_time":0.7182091642,"remaining_time":0.06757766753},
{"learn":[3.160416261],"iteration":914,"passed_time":0.7188536753,"remaining_time":0.06677875672},
{"learn":[3.15844291],"iteration":915,"passed_time":0.7195697974,"remaining_time":0.06598674998},
{"learn":[3.155040501],"iteration":916,"passed_time":0.7203239246,"remaining_time":0.06519834868},
{"learn":[3.154937548],"iteration":917,"passed_time":0.7209259146,"remaining_time":0.06439643246},
{"learn":[3.153721161],"iteration":918,"passed_time":0.7215261045,"remaining_time":0.06359479267},
{"learn":[3.153170511],"iteration":919,"passed_time":0.7221791756,"remaining_time":0.06279818919},
{"learn":[3.153113601],"iteration":920,"passed_time":0.7227984428,"remaining_time":0.06199899781},
{"learn":[3.150607379],"iteration":921,"passed_time":0.7234180637,"remaining_time":0.06120022665},
{"learn":[3.148408359],"iteration":922,"passed_time":0.7240328877,"remaining_time":0.0604014435},
{"learn":[3.147495728],"iteration":923,"passed_time":0.7247262452,"remaining_time":0.059609518},
{"learn":[3.146946235],"iteration":924,"passed_time":0.7253124041,"remaining_time":0.05880911384},
{"learn":[3.14472738],"iteration":925,"passed_time":0.7260340886,"remaining_time":0.05802000276},
{"learn":[3.144469477],"iteration":926,"passed_time":0.7267225208,"remaining_time":0.05722841857},
{"learn":[3.142975516],"iteration":927,"passed_time":0.7274362637,"remaining_time":0.05643902046},
{"learn":[3.14079113],"iteration":928,"passed_time":0.7280924703,"remaining_time":0.05564538793},
{"learn":[3.138173032],"iteration":929,"passed_time":0.7287487585,"remaining_time":0.05485205709},
{"learn":[3.136352813],"iteration":930,"passed_time":0.729302951,"remaining_time":0.05405145394},
{"learn":[3.133735004],"iteration":931,"passed_time":0.7298857649,"remaining_time":0.05325346783},
{"learn":[3.1319496],"iteration":932,"passed_time":0.7303902805,"remaining_time":0.05245032025},
{"learn":[3.129865343],"iteration":933,"passed_time":0.7309238659,"remaining_time":0.05164986632},
{"learn":[3.129830206],"iteration":934,"passed_time":0.7313223514,"remaining_time":0.05084059128},
{"learn":[3.126676562],"iteration":935,"passed_time":0.7318125813,"remaining_time":0.0500384671},
{"learn":[3.12645665],"iteration":936,"passed_time":0.7322969056,"remaining_time":0.04923661158},
{"learn":[3.126378007],"iteration":937,"passed_time":0.732908333,"remaining_time":0.04844383438},
{"learn":[3.124621914],"iteration":938,"passed_time":0.7336173869,"remaining_time":0.04765778552},
{"learn":[3.123379018],"iteration":939,"passed_time":0.7341449656,"remaining_time":0.04686031695},
{"learn":[3.123332451],"iteration":940,"passed_time":0.7346313623,"remaining_time":0.04606083993},
{"learn":[3.122432444],"iteration":941,"passed_time":0.7351673839,"remaining_time":0.04526508309},
{"learn":[3.121889006],"iteration":942,"passed_time":0.7356797074,"remaining_time":0.04446844467},
{"learn":[3.121070914],"iteration":943,"passed_time":0.7361826912,"remaining_time":0.04367185457},
{"learn":[3.118444705],"iteration":944,"passed_time":0.7367032593,"remaining_time":0.04287690927},
{"learn":[3.116820458],"iteration":945,"passed_time":0.7372406188,"remaining_time":0.04208350256},
{"learn":[3.114971041],"iteration":946,"passed_time":0.7378564775,"remaining_time":0.04129502989},
{"learn":[3.114685138],"iteration":947,"passed_time":0.7384543866,"remaining_time":0.04050593682},
{"learn":[3.113399363],"iteration":948,"passed_time":0.7390174914,"remaining_time":0.03971537625},
{"learn":[3.110575399],"iteration":949,"passed_time":0.7396674984,"remaining_time":0.03892986834},
{"learn":[3.110466553],"iteration":950,"passed_time":0.7403369801,"remaining_time":0.03814564882},
{"learn":[3.108691641],"iteration":951,"passed_time":0.7409649957,"remaining_time":0.03735957962},
{"learn":[3.107898017],"iteration":952,"passed_time":0.7414807105,"remaining_time":0.03656830366},
{"learn":[3.105551729],"iteration":953,"passed_time":0.7419867171,"remaining_time":0.0357771373},
{"learn":[3.104824945],"iteration":954,"passed_time":0.7426096669,"remaining_time":0.03499207854},
{"learn":[3.103186704],"iteration":955,"passed_time":0.7431466435,"remaining_time":0.034203402},
{"learn":[3.102330655],"iteration":956,"passed_time":0.7436846905,"remaining_time":0.03341529957},
{"learn":[3.102291298],"iteration":957,"passed_time":0.7441639333,"remaining_time":0.03262514113},
{"learn":[3.100363529],"iteration":958,"passed_time":0.7447493148,"remaining_time":0.03184016883},
{"learn":[3.097871596],"iteration":959,"passed_time":0.7452491218,"remaining_time":0.03105204674},
{"learn":[3.097372213],"iteration":960,"passed_time":0.7458165553,"remaining_time":0.03026726915},
{"learn":[3.095981813],"iteration":961,"passed_time":0.7463419555,"remaining_time":0.02948128307},
{"learn":[3.095347452],"iteration":962,"passed_time":0.7471426702,"remaining_time":0.0287064162},
{"learn":[3.094728409],"iteration":963,"passed_time":0.7477104878,"remaining_time":0.0279227983},
{"learn":[3.094118537],"iteration":964,"passed_time":0.7482456938,"remaining_time":0.02713844485},
{"learn":[3.093793695],"iteration":965,"passed_time":0.7488047809,"remaining_time":0.02635544777},
{"learn":[3.092581602],"iteration":966,"passed_time":0.7493256016,"remaining_time":0.02557160792},
{"learn":[3.091694202],"iteration":967,"passed_time":0.7498073136,"remaining_time":0.02478701863},
{"learn":[3.090298312],"iteration":968,"passed_time":0.7503062008,"remaining_time":0.02400360395},
{"learn":[3.090020107],"iteration":969,"passed_time":0.7508503528,"remaining_time":0.02322217586},
{"learn":[3.088949869],"iteration":970,"passed_time":0.7514757867,"remaining_time":0.02244366407},
{"learn":[3.086700204],"iteration":971,"passed_time":0.752037964,"remaining_time":0.02166364505},
{"learn":[3.086584317],"iteration":972,"passed_time":0.7527075449,"remaining_time":0.02088705418},
{"learn":[3.084850742],"iteration":973,"passed_time":0.7533515376,"remaining_time":0.02010999998},
{"learn":[3.084239948],"iteration":974,"passed_time":0.7540187401,"remaining_time":0.01933381385},
{"learn":[3.082561673],"iteration":975,"passed_time":0.7546287334,"remaining_time":0.01855644426},
{"learn":[3.07991814],"iteration":976,"passed_time":0.7551589042,"remaining_time":0.01777753817},
{"learn":[3.079350277],"iteration":977,"passed_time":0.7557542465,"remaining_time":0.01700060677},
{"learn":[3.077637462],"iteration":978,"passed_time":0.75630899,"remaining_time":0.01622317548},
{"learn":[3.076733301],"iteration":979,"passed_time":0.7568097727,"remaining_time":0.0154450974},
{"learn":[3.07594065],"iteration":980,"passed_time":0.7573172598,"remaining_time":0.01466771451},
{"learn":[3.072594655],"iteration":981,"passed_time":0.757857558,"remaining_time":0.01389148273},
{"learn":[3.071977674],"iteration":982,"passed_time":0.7583630439,"remaining_time":0.01311512894},
{"learn":[3.069532634],"iteration":983,"passed_time":0.7588456159,"remaining_time":0.0123389531},
{"learn":[3.068870784],"iteration":984,"passed_time":0.7593323404,"remaining_time":0.01156343666},
{"learn":[3.068801463],"iteration":985,"passed_time":0.7599563436,"remaining_time":0.01079045518},
{"learn":[3.067433249],"iteration":986,"passed_time":0.7606722118,"remaining_time":0.01001898557},
{"learn":[3.065611456],"iteration":987,"passed_time":0.7612342038,"remaining_time":0.00924575956},
{"learn":[3.063039162],"iteration":988,"passed_time":0.7617521549,"remaining_time":0.008472470883},
{"learn":[3.06177873],"iteration":989,"passed_time":0.7623089804,"remaining_time":0.007700090711},
{"learn":[3.061689148],"iteration":990,"passed_time":0.7627991046,"remaining_time":0.006927539799},
{"learn":[3.058984039],"iteration":991,"passed_time":0.7632931829,"remaining_time":0.006155590185},
{"learn":[3.057492984],"iteration":992,"passed_time":0.7638088188,"remaining_time":0.005384352197},
{"learn":[3.057290731],"iteration":993,"passed_time":0.7643284387,"remaining_time":0.004613652547},
{"learn":[3.056068348],"iteration":994,"passed_time":0.7648318942,"remaining_time":0.003843376353},
{"learn":[3.054987307],"iteration":995,"passed_time":0.7654530829,"remaining_time":0.003074108767},
{"learn":[3.054200234],"iteration":996,"passed_time":0.766040126,"remaining_time":0.002305035484},
{"learn":[3.052732869],"iteration":997,"passed_time":0.7666195334,"remaining_time":0.00153631169},
{"learn":[3.051787862],"iteration":998,"passed_time":0.7673243286,"remaining_time":0.0007680924211},
{"learn":[3.051366222],"iteration":999,"passed_time":0.7679588613,"remaining_time":0}
]}